{
  "ForYou": [
    {
      "file": "src/components/for-you/ForYouDetailPanel.tsx",
      "line": 20,
      "hex": "#09090B",
      "snippet": "ink: '#09090B', inkSecondary: '#18181B', inkTertiary: '#3F3F46',"
    },
    {
      "file": "src/components/for-you/ForYouDetailPanel.tsx",
      "line": 20,
      "hex": "#18181B",
      "snippet": "ink: '#09090B', inkSecondary: '#18181B', inkTertiary: '#3F3F46',"
    },
    {
      "file": "src/components/for-you/ForYouDetailPanel.tsx",
      "line": 20,
      "hex": "#3F3F46",
      "snippet": "ink: '#09090B', inkSecondary: '#18181B', inkTertiary: '#3F3F46',"
    },
    {
      "file": "src/components/for-you/ForYouDetailPanel.tsx",
      "line": 21,
      "hex": "#71717A",
      "snippet": "inkMuted: '#71717A', inkMutedStrong: '#6F6F78',"
    },
    {
      "file": "src/components/for-you/ForYouDetailPanel.tsx",
      "line": 21,
      "hex": "#6F6F78",
      "snippet": "inkMuted: '#71717A', inkMutedStrong: '#6F6F78',"
    },
    {
      "file": "src/components/for-you/ForYouDetailPanel.tsx",
      "line": 22,
      "hex": "#FAFAFA",
      "snippet": "surface: '#FFFFFF', surfaceSecondary: '#FAFAFA', surfaceTertiary: '#F4F4F5',"
    },
    {
      "file": "src/components/for-you/ForYouDetailPanel.tsx",
      "line": 22,
      "hex": "#F4F4F5",
      "snippet": "surface: '#FFFFFF', surfaceSecondary: '#FAFAFA', surfaceTertiary: '#F4F4F5',"
    },
    {
      "file": "src/components/for-you/ForYouDetailPanel.tsx",
      "line": 23,
      "hex": "#E4E4E7",
      "snippet": "border: '#E4E4E7', borderStrong: '#D4D4D8',"
    },
    {
      "file": "src/components/for-you/ForYouDetailPanel.tsx",
      "line": 23,
      "hex": "#D4D4D8",
      "snippet": "border: '#E4E4E7', borderStrong: '#D4D4D8',"
    },
    {
      "file": "src/components/for-you/ForYouDetailPanel.tsx",
      "line": 24,
      "hex": "#2563EB",
      "snippet": "primary: '#2563EB', primaryHover: '#1D4ED8', primaryBg: '#EFF6FF',"
    },
    {
      "file": "src/components/for-you/ForYouDetailPanel.tsx",
      "line": 24,
      "hex": "#1D4ED8",
      "snippet": "primary: '#2563EB', primaryHover: '#1D4ED8', primaryBg: '#EFF6FF',"
    },
    {
      "file": "src/components/for-you/ForYouDetailPanel.tsx",
      "line": 24,
      "hex": "#EFF6FF",
      "snippet": "primary: '#2563EB', primaryHover: '#1D4ED8', primaryBg: '#EFF6FF',"
    },
    {
      "file": "src/components/for-you/ForYouDetailPanel.tsx",
      "line": 25,
      "hex": "#0D9488",
      "snippet": "teal: '#0D9488', tealText: '#0A8277', tealBg: '#F0FDFA',"
    },
    {
      "file": "src/components/for-you/ForYouDetailPanel.tsx",
      "line": 25,
      "hex": "#0A8277",
      "snippet": "teal: '#0D9488', tealText: '#0A8277', tealBg: '#F0FDFA',"
    },
    {
      "file": "src/components/for-you/ForYouDetailPanel.tsx",
      "line": 25,
      "hex": "#F0FDFA",
      "snippet": "teal: '#0D9488', tealText: '#0A8277', tealBg: '#F0FDFA',"
    },
    {
      "file": "src/components/for-you/ForYouDetailPanel.tsx",
      "line": 26,
      "hex": "#16A34A",
      "snippet": "success: '#16A34A', successText: '#11853D', successBg: '#F0FDF4',"
    },
    {
      "file": "src/components/for-you/ForYouDetailPanel.tsx",
      "line": 26,
      "hex": "#11853D",
      "snippet": "success: '#16A34A', successText: '#11853D', successBg: '#F0FDF4',"
    },
    {
      "file": "src/components/for-you/ForYouDetailPanel.tsx",
      "line": 26,
      "hex": "#F0FDF4",
      "snippet": "success: '#16A34A', successText: '#11853D', successBg: '#F0FDF4',"
    },
    {
      "file": "src/components/for-you/ForYouDetailPanel.tsx",
      "line": 27,
      "hex": "#D97706",
      "snippet": "warning: '#D97706', warningText: '#AF6003', warningBg: '#FFFBEB',"
    },
    {
      "file": "src/components/for-you/ForYouDetailPanel.tsx",
      "line": 27,
      "hex": "#AF6003",
      "snippet": "warning: '#D97706', warningText: '#AF6003', warningBg: '#FFFBEB',"
    },
    {
      "file": "src/components/for-you/ForYouDetailPanel.tsx",
      "line": 27,
      "hex": "#FFFBEB",
      "snippet": "warning: '#D97706', warningText: '#AF6003', warningBg: '#FFFBEB',"
    },
    {
      "file": "src/components/for-you/ForYouDetailPanel.tsx",
      "line": 28,
      "hex": "#DC2626",
      "snippet": "danger: '#DC2626', dangerText: '#D92525', dangerBg: '#FEF2F2',"
    },
    {
      "file": "src/components/for-you/ForYouDetailPanel.tsx",
      "line": 28,
      "hex": "#D92525",
      "snippet": "danger: '#DC2626', dangerText: '#D92525', dangerBg: '#FEF2F2',"
    },
    {
      "file": "src/components/for-you/ForYouDetailPanel.tsx",
      "line": 28,
      "hex": "#FEF2F2",
      "snippet": "danger: '#DC2626', dangerText: '#D92525', dangerBg: '#FEF2F2',"
    },
    {
      "file": "src/components/for-you/ForYouDetailPanel.tsx",
      "line": 33,
      "hex": "#EDEDED",
      "snippet": "ink: '#EDEDED', inkSecondary: 'rgba(255,255,255,0.82)', inkTertiary: 'rgba(255,255,255,0.60)',"
    },
    {
      "file": "src/components/for-you/ForYouDetailPanel.tsx",
      "line": 35,
      "hex": "#1A1A1A",
      "snippet": "surface: '#1A1A1A', surfaceSecondary: '#0A0A0A', surfaceTertiary: '#1F1F1F',"
    },
    {
      "file": "src/components/for-you/ForYouDetailPanel.tsx",
      "line": 35,
      "hex": "#0A0A0A",
      "snippet": "surface: '#1A1A1A', surfaceSecondary: '#0A0A0A', surfaceTertiary: '#1F1F1F',"
    },
    {
      "file": "src/components/for-you/ForYouDetailPanel.tsx",
      "line": 35,
      "hex": "#1F1F1F",
      "snippet": "surface: '#1A1A1A', surfaceSecondary: '#0A0A0A', surfaceTertiary: '#1F1F1F',"
    },
    {
      "file": "src/components/for-you/ForYouDetailPanel.tsx",
      "line": 36,
      "hex": "#2E2E2E",
      "snippet": "border: '#2E2E2E', borderStrong: '#454545',"
    },
    {
      "file": "src/components/for-you/ForYouDetailPanel.tsx",
      "line": 36,
      "hex": "#454545",
      "snippet": "border: '#2E2E2E', borderStrong: '#454545',"
    }
  ],
  "StrategyHub": [
    {
      "file": "src/pages/strategyhub/GoalsKeyResultsPage.tsx",
      "line": 22,
      "hex": "#0A0A0A",
      "snippet": "bg: '#0A0A0A',"
    },
    {
      "file": "src/pages/strategyhub/GoalsKeyResultsPage.tsx",
      "line": 27,
      "hex": "#2E2E2E",
      "snippet": "border: '#2E2E2E',"
    },
    {
      "file": "src/pages/strategyhub/GoalsKeyResultsPage.tsx",
      "line": 28,
      "hex": "#2E2E2E",
      "snippet": "borderSubtle: '#2E2E2E',"
    },
    {
      "file": "src/pages/strategyhub/GoalsKeyResultsPage.tsx",
      "line": 29,
      "hex": "#1F1F1F",
      "snippet": "hover: '#1F1F1F',"
    },
    {
      "file": "src/pages/strategyhub/GoalsKeyResultsPage.tsx",
      "line": 124,
      "hex": "#64748B",
      "snippet": "<button onClick={exportCSV} style={{ display: 'inline-flex', alignItems: 'center', gap: 6, padding: '7px 14px', fontSize: 13, fontWeight: 50"
    },
    {
      "file": "src/pages/strategyhub/GoalsKeyResultsPage.tsx",
      "line": 124,
      "hex": "#E2E8F0",
      "snippet": "<button onClick={exportCSV} style={{ display: 'inline-flex', alignItems: 'center', gap: 6, padding: '7px 14px', fontSize: 13, fontWeight: 50"
    },
    {
      "file": "src/pages/strategyhub/GoalsKeyResultsPage.tsx",
      "line": 127,
      "hex": "#2563EB",
      "snippet": "<button onClick={() => setShowCreateModal(true)} style={{ display: 'inline-flex', alignItems: 'center', gap: 6, padding: '7px 16px', fontSiz"
    },
    {
      "file": "src/pages/strategyhub/GoalsKeyResultsPage.tsx",
      "line": 127,
      "hex": "#1D4ED8",
      "snippet": "<button onClick={() => setShowCreateModal(true)} style={{ display: 'inline-flex', alignItems: 'center', gap: 6, padding: '7px 16px', fontSiz"
    },
    {
      "file": "src/pages/strategyhub/StrategicThemesPage.tsx",
      "line": 111,
      "hex": "#1F1F1F",
      "snippet": "<div key={i} className=\"rounded-lg animate-pulse\" style={{ height: 48, background: isDark ? '#1F1F1F' : 'hsl(var(--muted))' }} />"
    },
    {
      "file": "src/pages/strategy/StrategyRoom.tsx",
      "line": 154,
      "hex": "#2563EB",
      "snippet": "style={{ background: '#2563EB', color: '#FFFFFF' }}"
    },
    {
      "file": "src/components/strategy/intelligence/AIStrategyIntelligencePanel.tsx",
      "line": 68,
      "hex": "#DBEAFE",
      "snippet": "{ bg: '#DBEAFE', text: '#1E40AF', border: '#93C5FD' },"
    },
    {
      "file": "src/components/strategy/intelligence/AIStrategyIntelligencePanel.tsx",
      "line": 68,
      "hex": "#1E40AF",
      "snippet": "{ bg: '#DBEAFE', text: '#1E40AF', border: '#93C5FD' },"
    },
    {
      "file": "src/components/strategy/intelligence/AIStrategyIntelligencePanel.tsx",
      "line": 68,
      "hex": "#93C5FD",
      "snippet": "{ bg: '#DBEAFE', text: '#1E40AF', border: '#93C5FD' },"
    },
    {
      "file": "src/components/strategy/intelligence/AIStrategyIntelligencePanel.tsx",
      "line": 69,
      "hex": "#CCFBF1",
      "snippet": "{ bg: '#CCFBF1', text: '#115E59', border: '#5EEAD4' },"
    },
    {
      "file": "src/components/strategy/intelligence/AIStrategyIntelligencePanel.tsx",
      "line": 69,
      "hex": "#115E59",
      "snippet": "{ bg: '#CCFBF1', text: '#115E59', border: '#5EEAD4' },"
    },
    {
      "file": "src/components/strategy/intelligence/AIStrategyIntelligencePanel.tsx",
      "line": 69,
      "hex": "#5EEAD4",
      "snippet": "{ bg: '#CCFBF1', text: '#115E59', border: '#5EEAD4' },"
    },
    {
      "file": "src/components/strategy/intelligence/AIStrategyIntelligencePanel.tsx",
      "line": 70,
      "hex": "#DBEAFE",
      "snippet": "{ bg: '#DBEAFE', text: '#1E40AF', border: '#93C5FD' },"
    },
    {
      "file": "src/components/strategy/intelligence/AIStrategyIntelligencePanel.tsx",
      "line": 70,
      "hex": "#1E40AF",
      "snippet": "{ bg: '#DBEAFE', text: '#1E40AF', border: '#93C5FD' },"
    },
    {
      "file": "src/components/strategy/intelligence/AIStrategyIntelligencePanel.tsx",
      "line": 70,
      "hex": "#93C5FD",
      "snippet": "{ bg: '#DBEAFE', text: '#1E40AF', border: '#93C5FD' },"
    },
    {
      "file": "src/components/strategy/intelligence/AIStrategyIntelligencePanel.tsx",
      "line": 71,
      "hex": "#FEF3C7",
      "snippet": "{ bg: '#FEF3C7', text: '#92400E', border: '#FDE68A' },"
    },
    {
      "file": "src/components/strategy/intelligence/AIStrategyIntelligencePanel.tsx",
      "line": 71,
      "hex": "#92400E",
      "snippet": "{ bg: '#FEF3C7', text: '#92400E', border: '#FDE68A' },"
    },
    {
      "file": "src/components/strategy/intelligence/AIStrategyIntelligencePanel.tsx",
      "line": 71,
      "hex": "#FDE68A",
      "snippet": "{ bg: '#FEF3C7', text: '#92400E', border: '#FDE68A' },"
    },
    {
      "file": "src/components/strategy/intelligence/AIStrategyIntelligencePanel.tsx",
      "line": 72,
      "hex": "#EDE9FE",
      "snippet": "{ bg: '#EDE9FE', text: '#5B21B6', border: '#C4B5FD' },"
    },
    {
      "file": "src/components/strategy/intelligence/AIStrategyIntelligencePanel.tsx",
      "line": 72,
      "hex": "#5B21B6",
      "snippet": "{ bg: '#EDE9FE', text: '#5B21B6', border: '#C4B5FD' },"
    },
    {
      "file": "src/components/strategy/intelligence/AIStrategyIntelligencePanel.tsx",
      "line": 72,
      "hex": "#C4B5FD",
      "snippet": "{ bg: '#EDE9FE', text: '#5B21B6', border: '#C4B5FD' },"
    },
    {
      "file": "src/components/strategy/intelligence/AIStrategyIntelligencePanel.tsx",
      "line": 92,
      "hex": "#2563EB",
      "snippet": "<div className=\"h-[2px] w-full shrink-0\" style={{ background: 'linear-gradient(90deg, #2563EB 0%, #60A5FA 50%, #2563EB 100%)' }} />"
    },
    {
      "file": "src/components/strategy/intelligence/AIStrategyIntelligencePanel.tsx",
      "line": 92,
      "hex": "#60A5FA",
      "snippet": "<div className=\"h-[2px] w-full shrink-0\" style={{ background: 'linear-gradient(90deg, #2563EB 0%, #60A5FA 50%, #2563EB 100%)' }} />"
    },
    {
      "file": "src/components/strategy/intelligence/AIStrategyIntelligencePanel.tsx",
      "line": 92,
      "hex": "#2563EB",
      "snippet": "<div className=\"h-[2px] w-full shrink-0\" style={{ background: 'linear-gradient(90deg, #2563EB 0%, #60A5FA 50%, #2563EB 100%)' }} />"
    },
    {
      "file": "src/components/strategy/intelligence/AIStrategyIntelligencePanel.tsx",
      "line": 97,
      "hex": "#2563EB",
      "snippet": "<div className=\"w-8 h-8 rounded-lg flex items-center justify-center shrink-0\" style={{ background: 'linear-gradient(135deg, #2563EB, #1E3A8A"
    },
    {
      "file": "src/components/strategy/intelligence/AIStrategyIntelligencePanel.tsx",
      "line": 97,
      "hex": "#1E3A8A",
      "snippet": "<div className=\"w-8 h-8 rounded-lg flex items-center justify-center shrink-0\" style={{ background: 'linear-gradient(135deg, #2563EB, #1E3A8A"
    }
  ],
  "ProductHub": [
    {
      "file": "src/pages/producthub/IdeasAnalyticsPage.tsx",
      "line": 15,
      "hex": "#DFE1E6",
      "snippet": "'Draft': '#DFE1E6', 'Submitted': '#DFE1E6', 'Under Review': '#0C66E4', 'Approved': '#0C66E4', 'Converted to Request': '#1B7F37',"
    },
    {
      "file": "src/pages/producthub/IdeasAnalyticsPage.tsx",
      "line": 15,
      "hex": "#DFE1E6",
      "snippet": "'Draft': '#DFE1E6', 'Submitted': '#DFE1E6', 'Under Review': '#0C66E4', 'Approved': '#0C66E4', 'Converted to Request': '#1B7F37',"
    },
    {
      "file": "src/pages/producthub/IdeasAnalyticsPage.tsx",
      "line": 15,
      "hex": "#0C66E4",
      "snippet": "'Draft': '#DFE1E6', 'Submitted': '#DFE1E6', 'Under Review': '#0C66E4', 'Approved': '#0C66E4', 'Converted to Request': '#1B7F37',"
    },
    {
      "file": "src/pages/producthub/IdeasAnalyticsPage.tsx",
      "line": 15,
      "hex": "#0C66E4",
      "snippet": "'Draft': '#DFE1E6', 'Submitted': '#DFE1E6', 'Under Review': '#0C66E4', 'Approved': '#0C66E4', 'Converted to Request': '#1B7F37',"
    },
    {
      "file": "src/pages/producthub/IdeasAnalyticsPage.tsx",
      "line": 15,
      "hex": "#1B7F37",
      "snippet": "'Draft': '#DFE1E6', 'Submitted': '#DFE1E6', 'Under Review': '#0C66E4', 'Approved': '#0C66E4', 'Converted to Request': '#1B7F37',"
    },
    {
      "file": "src/pages/producthub/IdeasAnalyticsPage.tsx",
      "line": 18,
      "hex": "#42526E",
      "snippet": "'Draft': '#42526E', 'Submitted': '#42526E', 'Under Review': '#FFFFFF', 'Approved': '#FFFFFF', 'Converted to Request': '#FFFFFF',"
    },
    {
      "file": "src/pages/producthub/IdeasAnalyticsPage.tsx",
      "line": 18,
      "hex": "#42526E",
      "snippet": "'Draft': '#42526E', 'Submitted': '#42526E', 'Under Review': '#FFFFFF', 'Approved': '#FFFFFF', 'Converted to Request': '#FFFFFF',"
    },
    {
      "file": "src/pages/producthub/IdeasAnalyticsPage.tsx",
      "line": 21,
      "hex": "#2E2E2E",
      "snippet": "'Draft': '#2E2E2E', 'Submitted': '#2E2E2E', 'Under Review': 'rgba(59,130,246,0.15)',"
    },
    {
      "file": "src/pages/producthub/IdeasAnalyticsPage.tsx",
      "line": 21,
      "hex": "#2E2E2E",
      "snippet": "'Draft': '#2E2E2E', 'Submitted': '#2E2E2E', 'Under Review': 'rgba(59,130,246,0.15)',"
    },
    {
      "file": "src/pages/producthub/IdeasAnalyticsPage.tsx",
      "line": 25,
      "hex": "#93C5FD",
      "snippet": "'Draft': 'rgba(255,255,255,0.72)', 'Submitted': 'rgba(255,255,255,0.72)', 'Under Review': '#93C5FD',"
    },
    {
      "file": "src/pages/producthub/IdeasAnalyticsPage.tsx",
      "line": 26,
      "hex": "#93C5FD",
      "snippet": "'Approved': '#93C5FD', 'Converted to Request': '#86EFAC',"
    },
    {
      "file": "src/pages/producthub/IdeasAnalyticsPage.tsx",
      "line": 26,
      "hex": "#86EFAC",
      "snippet": "'Approved': '#93C5FD', 'Converted to Request': '#86EFAC',"
    },
    {
      "file": "src/pages/producthub/IdeasAnalyticsPage.tsx",
      "line": 93,
      "hex": "#454545",
      "snippet": "const containerBorder = `1px solid ${isDark ? '#454545' : dk.border}`;"
    },
    {
      "file": "src/pages/producthub/IdeasAnalyticsPage.tsx",
      "line": 110,
      "hex": "#2563EB",
      "snippet": "<StatCard label=\"Pending Conversion\" value={String(pendingConversion)} subtitle=\"approved, awaiting conversion\" color=\"#2563EB\" isDark={isDa"
    },
    {
      "file": "src/pages/producthub/IdeasAnalyticsPage.tsx",
      "line": 126,
      "hex": "#2E2E2E",
      "snippet": "background: isDark ? (STATUS_BAR_COLORS_DARK[s.status] || '#2E2E2E') : (STATUS_BAR_COLORS[s.status] || '#DFE1E6'),"
    },
    {
      "file": "src/pages/producthub/IdeasAnalyticsPage.tsx",
      "line": 126,
      "hex": "#DFE1E6",
      "snippet": "background: isDark ? (STATUS_BAR_COLORS_DARK[s.status] || '#2E2E2E') : (STATUS_BAR_COLORS[s.status] || '#DFE1E6'),"
    },
    {
      "file": "src/pages/producthub/IdeasAnalyticsPage.tsx",
      "line": 128,
      "hex": "#42526E",
      "snippet": "color: isDark ? (STATUS_TEXT_COLORS_DARK[s.status] || dk.t2) : (STATUS_TEXT_COLORS[s.status] || '#42526E'),"
    },
    {
      "file": "src/pages/producthub/IdeasAnalyticsPage.tsx",
      "line": 143,
      "hex": "#E2E8F0",
      "snippet": "<span style={{ width: '40px', display: 'inline-flex', alignItems: 'center', justifyContent: 'center', height: 20, borderRadius: 4, fontSize:"
    },
    {
      "file": "src/pages/producthub/IdeasAnalyticsPage.tsx",
      "line": 143,
      "hex": "#94A3B8",
      "snippet": "<span style={{ width: '40px', display: 'inline-flex', alignItems: 'center', justifyContent: 'center', height: 20, borderRadius: 4, fontSize:"
    },
    {
      "file": "src/pages/producthub/IdeasAnalyticsPage.tsx",
      "line": 145,
      "hex": "#2563EB",
      "snippet": "<div style={{ width: `${(q.count / maxQuarter) * 100}%`, height: '100%', background: QUARTER_BADGE[q.quarter]?.bg || '#2563EB', borderRadius"
    },
    {
      "file": "src/pages/producthub/IdeasAnalyticsPage.tsx",
      "line": 162,
      "hex": "#0C66E4",
      "snippet": "<div style={{ width: `${(t.total / maxConvTheme) * 100}%`, height: '100%', background: isDark ? 'rgba(59,130,246,0.15)' : '#0C66E4', borderR"
    },
    {
      "file": "src/pages/producthub/IdeasAnalyticsPage.tsx",
      "line": 174,
      "hex": "#E2E8F0",
      "snippet": "<span style={{ width: '40px', display: 'inline-flex', alignItems: 'center', justifyContent: 'center', height: 20, borderRadius: 4, fontSize:"
    },
    {
      "file": "src/pages/producthub/IdeasAnalyticsPage.tsx",
      "line": 174,
      "hex": "#94A3B8",
      "snippet": "<span style={{ width: '40px', display: 'inline-flex', alignItems: 'center', justifyContent: 'center', height: 20, borderRadius: 4, fontSize:"
    },
    {
      "file": "src/pages/producthub/IdeasAnalyticsPage.tsx",
      "line": 176,
      "hex": "#2563EB",
      "snippet": "<div style={{ width: `${q.total > 0 ? (q.total / maxConvQ) * 100 : 0}%`, height: '100%', background: QUARTER_BADGE[q.quarter]?.bg || '#2563E"
    },
    {
      "file": "src/pages/producthub/IdeasAnalyticsPage.tsx",
      "line": 189,
      "hex": "#454545",
      "snippet": "<div style={{ background: '', border: `1px solid ${isDark ? '#454545' : dk.border}`, borderRadius: '6px', padding: '20px' }}>"
    },
    {
      "file": "src/pages/producthub/IdeasBacklogPage.tsx",
      "line": 38,
      "hex": "#2563EB",
      "snippet": "assignee: r.assigned_to_name ? { name: r.assigned_to_name, initials: r.assigned_to_name.split(' ').map(p => p[0]).join('').toUpperCase().sli"
    },
    {
      "file": "src/pages/producthub/IdeasBacklogPage.tsx",
      "line": 131,
      "hex": "#2563EB",
      "snippet": "<button onClick={() => setIntelligenceOpen(true)} style={{ background: '', color: '#2563EB', border: '1px solid #2563EB', borderRadius: '6px"
    },
    {
      "file": "src/pages/producthub/IdeasBacklogPage.tsx",
      "line": 131,
      "hex": "#2563EB",
      "snippet": "<button onClick={() => setIntelligenceOpen(true)} style={{ background: '', color: '#2563EB', border: '1px solid #2563EB', borderRadius: '6px"
    },
    {
      "file": "src/pages/producthub/IdeasBacklogPage.tsx",
      "line": 134,
      "hex": "#2563EB",
      "snippet": "<button onClick={() => setCreateOpen(true)} style={{ background: '#2563EB', color: '#FFF', border: 'none', borderRadius: '6px', padding: '8p"
    },
    {
      "file": "src/pages/producthub/IdeasBacklogPage.tsx",
      "line": 189,
      "hex": "#2563EB",
      "snippet": "background: isActive ? '#2563EB' : (''), color: isActive ? '#FFFFFF' : dk.t2,"
    }
  ],
  "ProjectHub": [
    {
      "file": "src/components/project-hub/CreateProjectModal.tsx",
      "line": 25,
      "hex": "#2563EB",
      "snippet": "name: '', key: '', department: '', description: '', icon: 'rocket', color: '#2563EB',"
    },
    {
      "file": "src/components/project-hub/CreateProjectModal.tsx",
      "line": 36,
      "hex": "#2563EB",
      "snippet": "setDetails({ name: '', key: '', department: '', description: '', icon: 'rocket', color: '#2563EB', lead_id: '', linkJira: false, jiraKey: ''"
    },
    {
      "file": "src/components/project-hub/CreateProjectModal.tsx",
      "line": 125,
      "hex": "#1A1A1A",
      "snippet": "className=\"relative flex flex-col animate-scale-in bg-white dark:bg-[#1A1A1A]\""
    },
    {
      "file": "src/components/project-hub/CreateProjectModal.tsx",
      "line": 135,
      "hex": "#EDEDED",
      "snippet": "<h2 className=\"text-[var(--fg-1)] dark:text-[#EDEDED]\" style={{ fontSize: 18, fontWeight: 700, fontFamily: 'var(--cp-font-heading)' }}>"
    },
    {
      "file": "src/components/project-hub/CreateProjectModal.tsx",
      "line": 140,
      "hex": "#F1F5F9",
      "snippet": "className=\"flex items-center justify-center rounded-md transition-colors hover:bg-[#F1F5F9] dark:hover:bg-[#1F1F1F]\""
    },
    {
      "file": "src/components/project-hub/CreateProjectModal.tsx",
      "line": 140,
      "hex": "#1F1F1F",
      "snippet": "className=\"flex items-center justify-center rounded-md transition-colors hover:bg-[#F1F5F9] dark:hover:bg-[#1F1F1F]\""
    },
    {
      "file": "src/components/project-hub/CreateProjectModal.tsx",
      "line": 143,
      "hex": "#64748B",
      "snippet": "<X size={18} className=\"text-[#64748B] dark:text-[#878787]\" />"
    },
    {
      "file": "src/components/project-hub/CreateProjectModal.tsx",
      "line": 143,
      "hex": "#878787",
      "snippet": "<X size={18} className=\"text-[#64748B] dark:text-[#878787]\" />"
    },
    {
      "file": "src/components/project-hub/CreateProjectModal.tsx",
      "line": 156,
      "hex": "#2E2E2E",
      "snippet": "<div className=\"flex items-center justify-between px-6 py-4 border-t border-[] dark:border-[#2E2E2E]\">"
    },
    {
      "file": "src/components/project-hub/CreateProjectModal.tsx",
      "line": 159,
      "hex": "#F8FAFC",
      "snippet": "className=\"rounded-md transition-colors hover:bg-[#F8FAFC] dark:hover:bg-[#1F1F1F] bg-white dark:bg-transparent border border-[] dark:border"
    },
    {
      "file": "src/components/project-hub/CreateProjectModal.tsx",
      "line": 159,
      "hex": "#1F1F1F",
      "snippet": "className=\"rounded-md transition-colors hover:bg-[#F8FAFC] dark:hover:bg-[#1F1F1F] bg-white dark:bg-transparent border border-[] dark:border"
    },
    {
      "file": "src/components/project-hub/CreateProjectModal.tsx",
      "line": 159,
      "hex": "#2E2E2E",
      "snippet": "className=\"rounded-md transition-colors hover:bg-[#F8FAFC] dark:hover:bg-[#1F1F1F] bg-white dark:bg-transparent border border-[] dark:border"
    },
    {
      "file": "src/components/project-hub/CreateProjectModal.tsx",
      "line": 159,
      "hex": "#334155",
      "snippet": "className=\"rounded-md transition-colors hover:bg-[#F8FAFC] dark:hover:bg-[#1F1F1F] bg-white dark:bg-transparent border border-[] dark:border"
    },
    {
      "file": "src/components/project-hub/CreateProjectModal.tsx",
      "line": 159,
      "hex": "#A1A1A1",
      "snippet": "className=\"rounded-md transition-colors hover:bg-[#F8FAFC] dark:hover:bg-[#1F1F1F] bg-white dark:bg-transparent border border-[] dark:border"
    },
    {
      "file": "src/components/project-hub/FilterDropdown.tsx",
      "line": 46,
      "hex": "#2563EB",
      "snippet": "className={`flex items-center gap-1.5 rounded-[6px] transition-colors focus-visible:outline-none focus-visible:ring-2 focus-visible:ring-[#2"
    },
    {
      "file": "src/components/project-hub/FilterDropdown.tsx",
      "line": 48,
      "hex": "#0D1526",
      "snippet": "? dark ? 'bg-[#0D1526] border-[#1E3A5F] text-[#4C9AFF]' : 'bg-[#DEEBFF] border-[#B3D4FF] text-[#0052CC]'"
    },
    {
      "file": "src/components/project-hub/FilterDropdown.tsx",
      "line": 48,
      "hex": "#1E3A5F",
      "snippet": "? dark ? 'bg-[#0D1526] border-[#1E3A5F] text-[#4C9AFF]' : 'bg-[#DEEBFF] border-[#B3D4FF] text-[#0052CC]'"
    },
    {
      "file": "src/components/project-hub/FilterDropdown.tsx",
      "line": 48,
      "hex": "#4C9AFF",
      "snippet": "? dark ? 'bg-[#0D1526] border-[#1E3A5F] text-[#4C9AFF]' : 'bg-[#DEEBFF] border-[#B3D4FF] text-[#0052CC]'"
    },
    {
      "file": "src/components/project-hub/FilterDropdown.tsx",
      "line": 48,
      "hex": "#DEEBFF",
      "snippet": "? dark ? 'bg-[#0D1526] border-[#1E3A5F] text-[#4C9AFF]' : 'bg-[#DEEBFF] border-[#B3D4FF] text-[#0052CC]'"
    },
    {
      "file": "src/components/project-hub/FilterDropdown.tsx",
      "line": 48,
      "hex": "#B3D4FF",
      "snippet": "? dark ? 'bg-[#0D1526] border-[#1E3A5F] text-[#4C9AFF]' : 'bg-[#DEEBFF] border-[#B3D4FF] text-[#0052CC]'"
    },
    {
      "file": "src/components/project-hub/FilterDropdown.tsx",
      "line": 48,
      "hex": "#0052CC",
      "snippet": "? dark ? 'bg-[#0D1526] border-[#1E3A5F] text-[#4C9AFF]' : 'bg-[#DEEBFF] border-[#B3D4FF] text-[#0052CC]'"
    },
    {
      "file": "src/components/project-hub/FilterDropdown.tsx",
      "line": 49,
      "hex": "#2E2E2E",
      "snippet": ": dark ? 'bg-transparent border-[#2E2E2E] text-[#A1A1A1]' : 'bg-white border-[#E2E8F0] text-[#42526E]'"
    },
    {
      "file": "src/components/project-hub/FilterDropdown.tsx",
      "line": 49,
      "hex": "#A1A1A1",
      "snippet": ": dark ? 'bg-transparent border-[#2E2E2E] text-[#A1A1A1]' : 'bg-white border-[#E2E8F0] text-[#42526E]'"
    },
    {
      "file": "src/components/project-hub/FilterDropdown.tsx",
      "line": 49,
      "hex": "#E2E8F0",
      "snippet": ": dark ? 'bg-transparent border-[#2E2E2E] text-[#A1A1A1]' : 'bg-white border-[#E2E8F0] text-[#42526E]'"
    },
    {
      "file": "src/components/project-hub/FilterDropdown.tsx",
      "line": 49,
      "hex": "#42526E",
      "snippet": ": dark ? 'bg-transparent border-[#2E2E2E] text-[#A1A1A1]' : 'bg-white border-[#E2E8F0] text-[#42526E]'"
    },
    {
      "file": "src/components/project-hub/FilterDropdown.tsx",
      "line": 67,
      "hex": "#0052CC",
      "snippet": "style={{ width: 18, height: 18, backgroundColor: '#0052CC', color: '#FFF', fontSize: 10, fontWeight: 600 }}"
    },
    {
      "file": "src/components/project-hub/FilterDropdown.tsx",
      "line": 76,
      "hex": "#1A1A1A",
      "snippet": "className={`absolute top-full left-0 mt-1 z-50 ${dark ? 'bg-[#1A1A1A] border-[#2E2E2E]' : 'bg-white border-[#E2E8F0]'}`}"
    },
    {
      "file": "src/components/project-hub/FilterDropdown.tsx",
      "line": 76,
      "hex": "#2E2E2E",
      "snippet": "className={`absolute top-full left-0 mt-1 z-50 ${dark ? 'bg-[#1A1A1A] border-[#2E2E2E]' : 'bg-white border-[#E2E8F0]'}`}"
    },
    {
      "file": "src/components/project-hub/FilterDropdown.tsx",
      "line": 76,
      "hex": "#E2E8F0",
      "snippet": "className={`absolute top-full left-0 mt-1 z-50 ${dark ? 'bg-[#1A1A1A] border-[#2E2E2E]' : 'bg-white border-[#E2E8F0]'}`}"
    },
    {
      "file": "src/components/project-hub/FilterDropdown.tsx",
      "line": 105,
      "hex": "#2E2E2E",
      "snippet": "<div className=\"flex items-center justify-between px-3 py-2\" style={{ borderTop: `1px solid ${dark ? '#2E2E2E' : '#E2E8F0'}` }}>"
    }
  ],
  "WorkHub": [
    {
      "file": "src/modules/work-hub/components/AllWorkDetailPanel.tsx",
      "line": 35,
      "hex": "#DFE1E6",
      "snippet": "'Backlog': { bg: 'bg-[#DFE1E6]', text: 'text-[#42526E]', label: 'BACKLOG' },"
    },
    {
      "file": "src/modules/work-hub/components/AllWorkDetailPanel.tsx",
      "line": 35,
      "hex": "#42526E",
      "snippet": "'Backlog': { bg: 'bg-[#DFE1E6]', text: 'text-[#42526E]', label: 'BACKLOG' },"
    },
    {
      "file": "src/modules/work-hub/components/AllWorkDetailPanel.tsx",
      "line": 36,
      "hex": "#DFE1E6",
      "snippet": "'To Do': { bg: 'bg-[#DFE1E6]', text: 'text-[#42526E]', label: 'TO DO' },"
    },
    {
      "file": "src/modules/work-hub/components/AllWorkDetailPanel.tsx",
      "line": 36,
      "hex": "#42526E",
      "snippet": "'To Do': { bg: 'bg-[#DFE1E6]', text: 'text-[#42526E]', label: 'TO DO' },"
    },
    {
      "file": "src/modules/work-hub/components/AllWorkDetailPanel.tsx",
      "line": 37,
      "hex": "#0C66E4",
      "snippet": "'In Progress': { bg: 'bg-[#0C66E4]', text: 'text-white', label: 'IN PROGRESS' },"
    },
    {
      "file": "src/modules/work-hub/components/AllWorkDetailPanel.tsx",
      "line": 38,
      "hex": "#EAE6FF",
      "snippet": "'Ready for QA': { bg: 'bg-[#EAE6FF]', text: 'text-[#403294]', label: 'READY FOR QA' },"
    },
    {
      "file": "src/modules/work-hub/components/AllWorkDetailPanel.tsx",
      "line": 38,
      "hex": "#403294",
      "snippet": "'Ready for QA': { bg: 'bg-[#EAE6FF]', text: 'text-[#403294]', label: 'READY FOR QA' },"
    },
    {
      "file": "src/modules/work-hub/components/AllWorkDetailPanel.tsx",
      "line": 39,
      "hex": "#1B7F37",
      "snippet": "'In Production': { bg: 'bg-[#1B7F37]', text: 'text-white', label: 'IN PRODUCTION' },"
    },
    {
      "file": "src/modules/work-hub/components/AllWorkDetailPanel.tsx",
      "line": 40,
      "hex": "#1B7F37",
      "snippet": "'Done': { bg: 'bg-[#1B7F37]', text: 'text-white', label: 'DONE' },"
    },
    {
      "file": "src/modules/work-hub/components/AllWorkDetailPanel.tsx",
      "line": 69,
      "hex": "#1A1A1A",
      "snippet": "<Button variant=\"ghost\" size=\"icon\" className={cn(\"h-7 w-7\", isDark ? \"hover:bg-[#1A1A1A]\" : \"hover:bg-[#F4F5F7]\")}>"
    },
    {
      "file": "src/modules/work-hub/components/AllWorkDetailPanel.tsx",
      "line": 69,
      "hex": "#F4F5F7",
      "snippet": "<Button variant=\"ghost\" size=\"icon\" className={cn(\"h-7 w-7\", isDark ? \"hover:bg-[#1A1A1A]\" : \"hover:bg-[#F4F5F7]\")}>"
    },
    {
      "file": "src/modules/work-hub/components/AllWorkDetailPanel.tsx",
      "line": 72,
      "hex": "#1A1A1A",
      "snippet": "<Button variant=\"ghost\" size=\"icon\" className={cn(\"h-7 w-7\", isDark ? \"hover:bg-[#1A1A1A]\" : \"hover:bg-[#F4F5F7]\")}>"
    },
    {
      "file": "src/modules/work-hub/components/AllWorkDetailPanel.tsx",
      "line": 72,
      "hex": "#F4F5F7",
      "snippet": "<Button variant=\"ghost\" size=\"icon\" className={cn(\"h-7 w-7\", isDark ? \"hover:bg-[#1A1A1A]\" : \"hover:bg-[#F4F5F7]\")}>"
    },
    {
      "file": "src/modules/work-hub/components/AllWorkDetailPanel.tsx",
      "line": 75,
      "hex": "#1A1A1A",
      "snippet": "<Button variant=\"ghost\" size=\"icon\" className={cn(\"h-7 w-7\", isDark ? \"hover:bg-[#1A1A1A]\" : \"hover:bg-[#F4F5F7]\")}>"
    },
    {
      "file": "src/modules/work-hub/components/AllWorkDetailPanel.tsx",
      "line": 75,
      "hex": "#F4F5F7",
      "snippet": "<Button variant=\"ghost\" size=\"icon\" className={cn(\"h-7 w-7\", isDark ? \"hover:bg-[#1A1A1A]\" : \"hover:bg-[#F4F5F7]\")}>"
    },
    {
      "file": "src/modules/work-hub/components/AllWorkDetailPanel.tsx",
      "line": 78,
      "hex": "#1A1A1A",
      "snippet": "<Button variant=\"ghost\" size=\"icon\" className={cn(\"h-7 w-7\", isDark ? \"hover:bg-[#1A1A1A]\" : \"hover:bg-[#F4F5F7]\")}>"
    },
    {
      "file": "src/modules/work-hub/components/AllWorkDetailPanel.tsx",
      "line": 78,
      "hex": "#F4F5F7",
      "snippet": "<Button variant=\"ghost\" size=\"icon\" className={cn(\"h-7 w-7\", isDark ? \"hover:bg-[#1A1A1A]\" : \"hover:bg-[#F4F5F7]\")}>"
    },
    {
      "file": "src/modules/work-hub/components/AllWorkDetailPanel.tsx",
      "line": 81,
      "hex": "#1A1A1A",
      "snippet": "<Button variant=\"ghost\" size=\"icon\" className={cn(\"h-7 w-7\", isDark ? \"hover:bg-[#1A1A1A]\" : \"hover:bg-[#F4F5F7]\")} onClick={onClose}>"
    },
    {
      "file": "src/modules/work-hub/components/AllWorkDetailPanel.tsx",
      "line": 81,
      "hex": "#F4F5F7",
      "snippet": "<Button variant=\"ghost\" size=\"icon\" className={cn(\"h-7 w-7\", isDark ? \"hover:bg-[#1A1A1A]\" : \"hover:bg-[#F4F5F7]\")} onClick={onClose}>"
    },
    {
      "file": "src/modules/work-hub/components/AllWorkDetailPanel.tsx",
      "line": 176,
      "hex": "#2E2E2E",
      "snippet": "border: isDark ? '1px solid #2E2E2E' : 'none',"
    },
    {
      "file": "src/modules/work-hub/components/AllWorkDetailPanel.tsx",
      "line": 245,
      "hex": "#2E2E2E",
      "snippet": "border: isDark ? '1px solid #2E2E2E' : 'none',"
    },
    {
      "file": "src/modules/work-hub/components/AllWorkTicketList.tsx",
      "line": 76,
      "hex": "#2563eb",
      "snippet": "? 'bg-[#2563eb]/10 border-l-2 border-l-[#2563eb]'"
    },
    {
      "file": "src/modules/work-hub/components/AllWorkTicketList.tsx",
      "line": 76,
      "hex": "#2563eb",
      "snippet": "? 'bg-[#2563eb]/10 border-l-2 border-l-[#2563eb]'"
    },
    {
      "file": "src/modules/work-hub/components/AllWorkTicketList.tsx",
      "line": 89,
      "hex": "#2563eb",
      "snippet": "<span className=\"text-[12px] font-medium text-[#2563eb] dark:text-[#60a5fa]\">{item.key}</span>"
    },
    {
      "file": "src/modules/work-hub/components/AllWorkTicketList.tsx",
      "line": 89,
      "hex": "#60a5fa",
      "snippet": "<span className=\"text-[12px] font-medium text-[#2563eb] dark:text-[#60a5fa]\">{item.key}</span>"
    },
    {
      "file": "src/modules/work-hub/components/AllWorkTicketList.tsx",
      "line": 109,
      "hex": "#2563eb",
      "snippet": "className=\"text-[10px] text-[#2563eb] dark:text-[#60a5fa] hover:underline flex items-center gap-0.5\""
    },
    {
      "file": "src/modules/work-hub/components/AllWorkTicketList.tsx",
      "line": 109,
      "hex": "#60a5fa",
      "snippet": "className=\"text-[10px] text-[#2563eb] dark:text-[#60a5fa] hover:underline flex items-center gap-0.5\""
    },
    {
      "file": "src/modules/work-hub/components/CreateVersionDialog.tsx",
      "line": 101,
      "hex": "#1A1A1A",
      "snippet": "className=\"sm:max-w-[500px] p-0 gap-0 bg-white dark:bg-[#1A1A1A]\""
    },
    {
      "file": "src/modules/work-hub/components/CreateVersionDialog.tsx",
      "line": 106,
      "hex": "#172B4D",
      "snippet": "<DialogTitle className=\"text-[20px] font-semibold text-[#172B4D]\">"
    },
    {
      "file": "src/modules/work-hub/components/CreateVersionDialog.tsx",
      "line": 114,
      "hex": "#6B778C",
      "snippet": "<p className=\"text-[13px] text-[#6B778C]\">"
    }
  ],
  "TaskHub": [],
  "ReleaseHub": [
    {
      "file": "src/pages/releasehub/AllChangesPage.tsx",
      "line": 39,
      "hex": "#2563EB",
      "snippet": "style={{ color: value === o.value ? '#2563EB' : ('') }}"
    },
    {
      "file": "src/pages/releasehub/AllChangesPage.tsx",
      "line": 105,
      "hex": "#EDEDED",
      "snippet": "<h1 className=\"text-[22px] font-extrabold\" style={{ fontFamily: RH.fontDisplay, color: isDark ? '#EDEDED' : RH.ink1 }}>All Changes</h1>"
    },
    {
      "file": "src/pages/releasehub/AllChangesPage.tsx",
      "line": 110,
      "hex": "#3B82F6",
      "snippet": "style={{ background: 'linear-gradient(to bottom, #3B82F6, #2563EB)', boxShadow: '0 1px 2px rgba(0,0,0,0.1)' }}>"
    },
    {
      "file": "src/pages/releasehub/AllChangesPage.tsx",
      "line": 110,
      "hex": "#2563EB",
      "snippet": "style={{ background: 'linear-gradient(to bottom, #3B82F6, #2563EB)', boxShadow: '0 1px 2px rgba(0,0,0,0.1)' }}>"
    },
    {
      "file": "src/pages/releasehub/AllChangesPage.tsx",
      "line": 121,
      "hex": "#2563EB",
      "snippet": "className=\"h-9 w-[280px] pl-9 pr-3 rounded text-[13px] focus:outline-none focus:ring-2 focus:ring-[#2563EB]/20 focus:border-[#2563EB]\""
    },
    {
      "file": "src/pages/releasehub/AllChangesPage.tsx",
      "line": 121,
      "hex": "#2563EB",
      "snippet": "className=\"h-9 w-[280px] pl-9 pr-3 rounded text-[13px] focus:outline-none focus:ring-2 focus:ring-[#2563EB]/20 focus:border-[#2563EB]\""
    },
    {
      "file": "src/pages/releasehub/AllChangesPage.tsx",
      "line": 130,
      "hex": "#2563EB",
      "snippet": "style={view === 'list' ? { background: '', color: '#2563EB' } : { color: '' }}>"
    },
    {
      "file": "src/pages/releasehub/AllChangesPage.tsx",
      "line": 135,
      "hex": "#2563EB",
      "snippet": "style={view === 'kanban' ? { background: '', color: '#2563EB' } : { color: '' }}>"
    },
    {
      "file": "src/pages/releasehub/AllChangesPage.tsx",
      "line": 181,
      "hex": "#2563EB",
      "snippet": "<span className=\"text-[13px] font-medium text-[#2563EB] hover:underline\" style={{ fontFamily: RH.fontMono }}>{c.chg_number}</span>"
    },
    {
      "file": "src/pages/releasehub/AllChangesPage.tsx",
      "line": 189,
      "hex": "#2563EB",
      "snippet": "{relName ? <span className=\"text-[12px] font-medium text-[#2563EB]\">{relName}</span> : <span style={{ color: '' }}>—</span>}"
    },
    {
      "file": "src/pages/releasehub/AllChangesPage.tsx",
      "line": 234,
      "hex": "#2563EB",
      "snippet": "<span className=\"text-[11px] font-medium text-[#2563EB] block mb-1\" style={{ fontFamily: RH.fontMono }}>{c.chg_number}</span>"
    },
    {
      "file": "src/pages/releasehub/AllReleasesPage.tsx",
      "line": 72,
      "hex": "#2563EB",
      "snippet": "if (s === 'in_progress') return '#2563EB';"
    },
    {
      "file": "src/pages/releasehub/AllReleasesPage.tsx",
      "line": 73,
      "hex": "#16A34A",
      "snippet": "if (s === 'released') return '#16A34A';"
    },
    {
      "file": "src/pages/releasehub/AllReleasesPage.tsx",
      "line": 108,
      "hex": "#EDEDED",
      "snippet": "<h1 className=\"text-[22px] font-extrabold\" style={{ fontFamily: RH.fontDisplay, color: isDark ? '#EDEDED' : RH.ink1 }}>All Releases</h1>"
    },
    {
      "file": "src/pages/releasehub/AllReleasesPage.tsx",
      "line": 118,
      "hex": "#2563EB",
      "snippet": "className=\"h-9 px-4 rounded-md bg-[#2563EB] hover:bg-[#1D4ED8] text-white text-[13px] font-semibold flex items-center gap-1.5 active:scale-["
    },
    {
      "file": "src/pages/releasehub/AllReleasesPage.tsx",
      "line": 118,
      "hex": "#1D4ED8",
      "snippet": "className=\"h-9 px-4 rounded-md bg-[#2563EB] hover:bg-[#1D4ED8] text-white text-[13px] font-semibold flex items-center gap-1.5 active:scale-["
    },
    {
      "file": "src/pages/releasehub/AllReleasesPage.tsx",
      "line": 127,
      "hex": "#FEF3C7",
      "snippet": "background: '#FEF3C7',"
    },
    {
      "file": "src/pages/releasehub/AllReleasesPage.tsx",
      "line": 128,
      "hex": "#FCD34D",
      "snippet": "border: '1px solid #FCD34D',"
    },
    {
      "file": "src/pages/releasehub/AllReleasesPage.tsx",
      "line": 136,
      "hex": "#D97706",
      "snippet": "<AlertTriangle size={16} color=\"#D97706\" />"
    },
    {
      "file": "src/pages/releasehub/AllReleasesPage.tsx",
      "line": 137,
      "hex": "#92400E",
      "snippet": "<span style={{ fontSize: '13px', color: '#92400E' }}>"
    },
    {
      "file": "src/pages/releasehub/AllReleasesPage.tsx",
      "line": 143,
      "hex": "#B45309",
      "snippet": "style={{ color: '#B45309', textDecoration: 'underline', fontWeight: 600 }}>"
    },
    {
      "file": "src/pages/releasehub/AllReleasesPage.tsx",
      "line": 161,
      "hex": "#2563EB",
      "snippet": "? { borderColor: '#2563EB', background: '', color: '#2563EB' }"
    },
    {
      "file": "src/pages/releasehub/AllReleasesPage.tsx",
      "line": 161,
      "hex": "#2563EB",
      "snippet": "? { borderColor: '#2563EB', background: '', color: '#2563EB' }"
    },
    {
      "file": "src/pages/releasehub/AllReleasesPage.tsx",
      "line": 176,
      "hex": "#2563EB",
      "snippet": "className=\"h-9 w-64 pl-9 pr-3 rounded text-[13px] focus:outline-none focus:ring-2 focus:ring-[#2563EB]/20 focus:border-[#2563EB]\""
    },
    {
      "file": "src/pages/releasehub/AllReleasesPage.tsx",
      "line": 176,
      "hex": "#2563EB",
      "snippet": "className=\"h-9 w-64 pl-9 pr-3 rounded text-[13px] focus:outline-none focus:ring-2 focus:ring-[#2563EB]/20 focus:border-[#2563EB]\""
    },
    {
      "file": "src/pages/releasehub/AllReleasesPage.tsx",
      "line": 180,
      "hex": "#2563EB",
      "snippet": "<button onClick={() => setView('cards')} className=\"h-7 w-7 rounded flex items-center justify-center\" style={view === 'cards' ? { background"
    },
    {
      "file": "src/pages/releasehub/AllReleasesPage.tsx",
      "line": 181,
      "hex": "#2563EB",
      "snippet": "<button onClick={() => setView('table')} className=\"h-7 w-7 rounded flex items-center justify-center\" style={view === 'table' ? { background"
    },
    {
      "file": "src/pages/releasehub/AllReleasesPage.tsx",
      "line": 206,
      "hex": "#EDEDED",
      "snippet": "<h3 className=\"text-[15px] font-bold mb-1\" style={{ fontFamily: RH.fontDisplay, color: isDark ? '#EDEDED' : RH.ink1, fontWeight: 650 }}>{r.n"
    },
    {
      "file": "src/pages/releasehub/AllReleasesPage.tsx",
      "line": 217,
      "hex": "#94A3B8",
      "snippet": "<span className=\"inline-flex items-center gap-1 text-[11px] text-[#94A3B8] cursor-default\">"
    },
    {
      "file": "src/pages/releasehub/AllReleasesPage.tsx",
      "line": 270,
      "hex": "#EDEDED",
      "snippet": "<td className=\"px-3 py-0 font-medium\" style={{ color: isDark ? '#EDEDED' : RH.ink1 }}>"
    }
  ],
  "TestHub": [
    {
      "file": "src/pages/testhub/ActivityFeedPage.tsx",
      "line": 36,
      "hex": "#059669",
      "snippet": "create: { label: 'Created', color: '#059669', icon: Plus },"
    },
    {
      "file": "src/pages/testhub/ActivityFeedPage.tsx",
      "line": 37,
      "hex": "#2563EB",
      "snippet": "update: { label: 'Updated', color: '#2563EB', icon: Edit2 },"
    },
    {
      "file": "src/pages/testhub/ActivityFeedPage.tsx",
      "line": 38,
      "hex": "#DC2626",
      "snippet": "delete: { label: 'Deleted', color: '#DC2626', icon: Trash2 },"
    },
    {
      "file": "src/pages/testhub/ActivityFeedPage.tsx",
      "line": 39,
      "hex": "#7C3AED",
      "snippet": "execute: { label: 'Executed', color: '#7C3AED', icon: Play },"
    },
    {
      "file": "src/pages/testhub/ActivityFeedPage.tsx",
      "line": 40,
      "hex": "#0891B2",
      "snippet": "assign: { label: 'Assigned', color: '#0891B2', icon: UserPlus },"
    },
    {
      "file": "src/pages/testhub/ActivityFeedPage.tsx",
      "line": 41,
      "hex": "#D97706",
      "snippet": "status_change: { label: 'Status Changed', color: '#D97706', icon: ArrowRight },"
    },
    {
      "file": "src/pages/testhub/ActivityFeedPage.tsx",
      "line": 42,
      "hex": "#64748B",
      "snippet": "view: { label: 'Viewed', color: '#64748B', icon: Activity },"
    },
    {
      "file": "src/pages/testhub/ActivityFeedPage.tsx",
      "line": 43,
      "hex": "#EC4899",
      "snippet": "export: { label: 'Exported', color: '#EC4899', icon: Activity },"
    },
    {
      "file": "src/pages/testhub/ActivityFeedPage.tsx",
      "line": 44,
      "hex": "#EC4899",
      "snippet": "import: { label: 'Imported', color: '#EC4899', icon: Activity },"
    },
    {
      "file": "src/pages/testhub/ActivityFeedPage.tsx",
      "line": 48,
      "hex": "#2563EB",
      "snippet": "test_case: { label: 'Test Case', color: '#2563EB', icon: FileText },"
    },
    {
      "file": "src/pages/testhub/ActivityFeedPage.tsx",
      "line": 49,
      "hex": "#DC2626",
      "snippet": "defect: { label: 'Defect', color: '#DC2626', icon: Bug },"
    },
    {
      "file": "src/pages/testhub/ActivityFeedPage.tsx",
      "line": 50,
      "hex": "#0891B2",
      "snippet": "test_cycle: { label: 'Test Cycle', color: '#0891B2', icon: RefreshCcw },"
    },
    {
      "file": "src/pages/testhub/ActivityFeedPage.tsx",
      "line": 51,
      "hex": "#7C3AED",
      "snippet": "test_plan: { label: 'Test Plan', color: '#7C3AED', icon: ClipboardList },"
    },
    {
      "file": "src/pages/testhub/ActivityFeedPage.tsx",
      "line": 52,
      "hex": "#059669",
      "snippet": "requirement: { label: 'Requirement', color: '#059669', icon: FileCheck },"
    },
    {
      "file": "src/pages/testhub/ActivityFeedPage.tsx",
      "line": 53,
      "hex": "#6366F1",
      "snippet": "environment: { label: 'Environment', color: '#6366F1', icon: Server },"
    },
    {
      "file": "src/pages/testhub/ActivityFeedPage.tsx",
      "line": 54,
      "hex": "#EC4899",
      "snippet": "tag: { label: 'Tag', color: '#EC4899', icon: Tags },"
    },
    {
      "file": "src/pages/testhub/ActivityFeedPage.tsx",
      "line": 159,
      "hex": "#ECFDF5",
      "snippet": "<div style={{ backgroundColor: '#ECFDF5', borderRadius: 12, padding: 16, border: '1px solid #A7F3D0' }}>"
    },
    {
      "file": "src/pages/testhub/ActivityFeedPage.tsx",
      "line": 159,
      "hex": "#A7F3D0",
      "snippet": "<div style={{ backgroundColor: '#ECFDF5', borderRadius: 12, padding: 16, border: '1px solid #A7F3D0' }}>"
    },
    {
      "file": "src/pages/testhub/ActivityFeedPage.tsx",
      "line": 160,
      "hex": "#059669",
      "snippet": "<p style={{ fontSize: 11, color: '#059669', margin: 0, textTransform: 'uppercase' }}>Created</p>"
    },
    {
      "file": "src/pages/testhub/ActivityFeedPage.tsx",
      "line": 161,
      "hex": "#059669",
      "snippet": "<p style={{ fontSize: 24, fontWeight: 700, color: '#059669', margin: '4px 0 0' }}>{stats.creates}</p>"
    },
    {
      "file": "src/pages/testhub/ActivityFeedPage.tsx",
      "line": 163,
      "hex": "#EFF6FF",
      "snippet": "<div style={{ backgroundColor: '#EFF6FF', borderRadius: 12, padding: 16, border: '1px solid #BFDBFE' }}>"
    },
    {
      "file": "src/pages/testhub/ActivityFeedPage.tsx",
      "line": 163,
      "hex": "#BFDBFE",
      "snippet": "<div style={{ backgroundColor: '#EFF6FF', borderRadius: 12, padding: 16, border: '1px solid #BFDBFE' }}>"
    },
    {
      "file": "src/pages/testhub/ActivityFeedPage.tsx",
      "line": 164,
      "hex": "#2563EB",
      "snippet": "<p style={{ fontSize: 11, color: '#2563EB', margin: 0, textTransform: 'uppercase' }}>Updated</p>"
    },
    {
      "file": "src/pages/testhub/ActivityFeedPage.tsx",
      "line": 165,
      "hex": "#2563EB",
      "snippet": "<p style={{ fontSize: 24, fontWeight: 700, color: '#2563EB', margin: '4px 0 0' }}>{stats.updates}</p>"
    },
    {
      "file": "src/pages/testhub/ActivityFeedPage.tsx",
      "line": 167,
      "hex": "#FEF2F2",
      "snippet": "<div style={{ backgroundColor: '#FEF2F2', borderRadius: 12, padding: 16, border: '1px solid #FECACA' }}>"
    },
    {
      "file": "src/pages/testhub/ActivityFeedPage.tsx",
      "line": 167,
      "hex": "#FECACA",
      "snippet": "<div style={{ backgroundColor: '#FEF2F2', borderRadius: 12, padding: 16, border: '1px solid #FECACA' }}>"
    },
    {
      "file": "src/pages/testhub/ActivityFeedPage.tsx",
      "line": 168,
      "hex": "#DC2626",
      "snippet": "<p style={{ fontSize: 11, color: '#DC2626', margin: 0, textTransform: 'uppercase' }}>Deleted</p>"
    },
    {
      "file": "src/pages/testhub/ActivityFeedPage.tsx",
      "line": 169,
      "hex": "#DC2626",
      "snippet": "<p style={{ fontSize: 24, fontWeight: 700, color: '#DC2626', margin: '4px 0 0' }}>{stats.deletes}</p>"
    },
    {
      "file": "src/pages/testhub/ActivityFeedPage.tsx",
      "line": 181,
      "hex": "#94A3B8",
      "snippet": "<Search size={18} style={{ position: 'absolute', left: 14, top: '50%', transform: 'translateY(-50%)', color: '#94A3B8' }} />"
    },
    {
      "file": "src/pages/testhub/ActivityFeedPage.tsx",
      "line": 183,
      "hex": "#EDEDED",
      "snippet": "style={{ width: '100%', height: 44, padding: '0 14px 0 44px', border: `1.5px solid ${''}`, borderRadius: 12, fontSize: 14, backgroundColor: "
    }
  ],
  "IncidentHub": [
    {
      "file": "src/pages/incidenthub/CommitteeQueuePage.tsx",
      "line": 30,
      "hex": "#FEF3C7",
      "snippet": "<div className=\"flex items-center justify-center rounded-md\" style={{ width: 32, height: 32, backgroundColor: '#FEF3C7' }}>"
    },
    {
      "file": "src/pages/incidenthub/CommitteeQueuePage.tsx",
      "line": 31,
      "hex": "#D97706",
      "snippet": "<Users size={18} style={{ color: '#D97706' }} />"
    },
    {
      "file": "src/pages/incidenthub/CommitteeQueuePage.tsx",
      "line": 35,
      "hex": "#2563EB",
      "snippet": "<Button size=\"sm\" className=\"gap-1.5\" style={{ backgroundColor: '#2563EB', borderRadius: 6 }}>"
    },
    {
      "file": "src/pages/incidenthub/CommitteeQueuePage.tsx",
      "line": 41,
      "hex": "#2E2E2E",
      "snippet": "<div style={{ border: isDark ? '1px solid #2E2E2E' : '1px solid rgba(15,23,42,0.12)', borderRadius: 6, overflow: 'hidden' }}>"
    },
    {
      "file": "src/pages/incidenthub/CommitteeQueuePage.tsx",
      "line": 47,
      "hex": "#292929",
      "snippet": "borderBottom: isDark ? '0.75px solid #292929' : '0.75px solid rgba(15,23,42,0.06)',"
    },
    {
      "file": "src/pages/incidenthub/CommitteeQueuePage.tsx",
      "line": 78,
      "hex": "#292929",
      "snippet": "borderBottom: isDark ? '0.75px solid #292929' : '0.75px solid rgba(15,23,42,0.06)',"
    },
    {
      "file": "src/pages/incidenthub/CommitteeQueuePage.tsx",
      "line": 86,
      "hex": "#2563EB",
      "snippet": "<span style={{ fontFamily: 'var(--cp-font-mono)', fontSize: 12, color: '#2563EB', backgroundColor: '', padding: '0 4px', borderRadius: 3 }}>"
    },
    {
      "file": "src/pages/incidenthub/CommitteeQueuePage.tsx",
      "line": 103,
      "hex": "#16A34A",
      "snippet": "backgroundColor: progress >= 0.6 ? '#16A34A' : '#D97706',"
    },
    {
      "file": "src/pages/incidenthub/CommitteeQueuePage.tsx",
      "line": 103,
      "hex": "#D97706",
      "snippet": "backgroundColor: progress >= 0.6 ? '#16A34A' : '#D97706',"
    },
    {
      "file": "src/pages/incidenthub/CommitteeQueuePage.tsx",
      "line": 114,
      "hex": "#DC2626",
      "snippet": "<span className=\"inline-flex items-center gap-1\" style={{ fontSize: 10, fontWeight: 700, color: '#DC2626' }}>"
    },
    {
      "file": "src/pages/incidenthub/CommitteeQueuePage.tsx",
      "line": 115,
      "hex": "#DC2626",
      "snippet": "<span style={{ width: 6, height: 6, borderRadius: '50%', backgroundColor: '#DC2626', display: 'inline-block' }} />"
    },
    {
      "file": "src/pages/incidenthub/IncidentAnalyticsPage.tsx",
      "line": 42,
      "hex": "#DC2626",
      "snippet": "SEV1: '#DC2626', SEV2: '#D97706', SEV3: '#2563EB', SEV4: '#94A3B8',"
    },
    {
      "file": "src/pages/incidenthub/IncidentAnalyticsPage.tsx",
      "line": 42,
      "hex": "#D97706",
      "snippet": "SEV1: '#DC2626', SEV2: '#D97706', SEV3: '#2563EB', SEV4: '#94A3B8',"
    },
    {
      "file": "src/pages/incidenthub/IncidentAnalyticsPage.tsx",
      "line": 42,
      "hex": "#2563EB",
      "snippet": "SEV1: '#DC2626', SEV2: '#D97706', SEV3: '#2563EB', SEV4: '#94A3B8',"
    },
    {
      "file": "src/pages/incidenthub/IncidentAnalyticsPage.tsx",
      "line": 42,
      "hex": "#94A3B8",
      "snippet": "SEV1: '#DC2626', SEV2: '#D97706', SEV3: '#2563EB', SEV4: '#94A3B8',"
    },
    {
      "file": "src/pages/incidenthub/IncidentAnalyticsPage.tsx",
      "line": 46,
      "hex": "#DFE1E6",
      "snippet": "open: '#DFE1E6', triage: '#DFE1E6', in_progress: '#0C66E4', to_committee: '#0C66E4',"
    },
    {
      "file": "src/pages/incidenthub/IncidentAnalyticsPage.tsx",
      "line": 46,
      "hex": "#DFE1E6",
      "snippet": "open: '#DFE1E6', triage: '#DFE1E6', in_progress: '#0C66E4', to_committee: '#0C66E4',"
    },
    {
      "file": "src/pages/incidenthub/IncidentAnalyticsPage.tsx",
      "line": 46,
      "hex": "#0C66E4",
      "snippet": "open: '#DFE1E6', triage: '#DFE1E6', in_progress: '#0C66E4', to_committee: '#0C66E4',"
    },
    {
      "file": "src/pages/incidenthub/IncidentAnalyticsPage.tsx",
      "line": 46,
      "hex": "#0C66E4",
      "snippet": "open: '#DFE1E6', triage: '#DFE1E6', in_progress: '#0C66E4', to_committee: '#0C66E4',"
    },
    {
      "file": "src/pages/incidenthub/IncidentAnalyticsPage.tsx",
      "line": 47,
      "hex": "#0C66E4",
      "snippet": "in_review: '#0C66E4', resolved: '#1B7F37', closed: '#DFE1E6', converted: '#1B7F37',"
    },
    {
      "file": "src/pages/incidenthub/IncidentAnalyticsPage.tsx",
      "line": 47,
      "hex": "#1B7F37",
      "snippet": "in_review: '#0C66E4', resolved: '#1B7F37', closed: '#DFE1E6', converted: '#1B7F37',"
    },
    {
      "file": "src/pages/incidenthub/IncidentAnalyticsPage.tsx",
      "line": 47,
      "hex": "#DFE1E6",
      "snippet": "in_review: '#0C66E4', resolved: '#1B7F37', closed: '#DFE1E6', converted: '#1B7F37',"
    },
    {
      "file": "src/pages/incidenthub/IncidentAnalyticsPage.tsx",
      "line": 47,
      "hex": "#1B7F37",
      "snippet": "in_review: '#0C66E4', resolved: '#1B7F37', closed: '#DFE1E6', converted: '#1B7F37',"
    },
    {
      "file": "src/pages/incidenthub/IncidentAnalyticsPage.tsx",
      "line": 58,
      "hex": "#EFF6FF",
      "snippet": "<div className=\"flex items-center justify-center rounded-md\" style={{ width: 32, height: 32, backgroundColor: '#EFF6FF' }}>"
    },
    {
      "file": "src/pages/incidenthub/IncidentAnalyticsPage.tsx",
      "line": 59,
      "hex": "#2563EB",
      "snippet": "<BarChart3 size={18} style={{ color: '#2563EB' }} />"
    },
    {
      "file": "src/pages/incidenthub/IncidentAnalyticsPage.tsx",
      "line": 62,
      "hex": "#0F172A",
      "snippet": "<h1 style={{ fontFamily: 'var(--cp-font-heading)', fontSize: 18, fontWeight: 700, color: '#0F172A' }}>Analytics</h1>"
    },
    {
      "file": "src/pages/incidenthub/IncidentAnalyticsPage.tsx",
      "line": 63,
      "hex": "#64748B",
      "snippet": "<p style={{ fontFamily: 'var(--cp-font-body)', fontSize: 12, color: '#64748B' }}>Incident management metrics and trends</p>"
    },
    {
      "file": "src/pages/incidenthub/IncidentAnalyticsPage.tsx",
      "line": 70,
      "hex": "#2563EB",
      "snippet": "{ label: 'Avg Resolution', value: '\\u2014', accent: '#2563EB' },"
    },
    {
      "file": "src/pages/incidenthub/IncidentAnalyticsPage.tsx",
      "line": 71,
      "hex": "#DC2626",
      "snippet": "{ label: 'SLA Breach Rate', value: incidents ? `${Math.round((incidents.filter(i => i.resolution_breached).length / Math.max(incidents.lengt"
    },
    {
      "file": "src/pages/incidenthub/IncidentAnalyticsPage.tsx",
      "line": 72,
      "hex": "#0F172A",
      "snippet": "{ label: 'Total Incidents', value: stats.total, accent: '#0F172A' },"
    }
  ],
  "ResourceHub": [
    {
      "file": "src/pages/r360-member/BoardView.tsx",
      "line": 17,
      "hex": "#D97706",
      "snippet": "{ key: 'to_do', label: 'TO DO', color: '#D97706', items: items.filter(i => i.status_category === 'to_do' || i.status_category === 'blocked')"
    },
    {
      "file": "src/pages/r360-member/BoardView.tsx",
      "line": 18,
      "hex": "#2563EB",
      "snippet": "{ key: 'in_progress', label: 'IN PROGRESS', color: '#2563EB', items: items.filter(i => i.status_category === 'in_progress' || i.status_categ"
    },
    {
      "file": "src/pages/r360-member/BoardView.tsx",
      "line": 19,
      "hex": "#16A34A",
      "snippet": "{ key: 'done', label: 'DONE', color: '#16A34A', items: items.filter(i => i.status_category === 'done') },"
    },
    {
      "file": "src/pages/r360-member/BoardView.tsx",
      "line": 46,
      "hex": "#7C3AED",
      "snippet": "<div style={{ position: 'absolute', left: 0, top: 8, bottom: 8, width: 3, borderRadius: '0 2px 2px 0', background: item.role_on_item === 'Co"
    },
    {
      "file": "src/pages/r360-member/ChronologyView.tsx",
      "line": 58,
      "hex": "#2563EB",
      "snippet": "const accentColor = (cat: string) => cat === 'in_progress' ? '#2563EB' : cat === 'in_qa' ? '#0D9488' : cat === 'blocked' ? '#EF4444' : cat ="
    },
    {
      "file": "src/pages/r360-member/ChronologyView.tsx",
      "line": 58,
      "hex": "#0D9488",
      "snippet": "const accentColor = (cat: string) => cat === 'in_progress' ? '#2563EB' : cat === 'in_qa' ? '#0D9488' : cat === 'blocked' ? '#EF4444' : cat ="
    },
    {
      "file": "src/pages/r360-member/ChronologyView.tsx",
      "line": 58,
      "hex": "#EF4444",
      "snippet": "const accentColor = (cat: string) => cat === 'in_progress' ? '#2563EB' : cat === 'in_qa' ? '#0D9488' : cat === 'blocked' ? '#EF4444' : cat ="
    },
    {
      "file": "src/pages/r360-member/ChronologyView.tsx",
      "line": 58,
      "hex": "#16A34A",
      "snippet": "const accentColor = (cat: string) => cat === 'in_progress' ? '#2563EB' : cat === 'in_qa' ? '#0D9488' : cat === 'blocked' ? '#EF4444' : cat ="
    },
    {
      "file": "src/pages/r360-member/ChronologyView.tsx",
      "line": 58,
      "hex": "#D97706",
      "snippet": "const accentColor = (cat: string) => cat === 'in_progress' ? '#2563EB' : cat === 'in_qa' ? '#0D9488' : cat === 'blocked' ? '#EF4444' : cat ="
    },
    {
      "file": "src/pages/r360-member/ChronologyView.tsx",
      "line": 68,
      "hex": "#7C3AED",
      "snippet": "<div style={{ position: 'absolute', left: 0, top: 8, bottom: 8, width: 3, borderRadius: '0 2px 2px 0', background: item.role_on_item === 'Co"
    },
    {
      "file": "src/pages/r360-member/ChronologyView.tsx",
      "line": 142,
      "hex": "#16A34A",
      "snippet": "{statusDist.done > 0 && <div style={{ width: `${statusDist.done / total * 100}%`, background: '#16A34A' }} />}"
    },
    {
      "file": "src/pages/r360-member/ChronologyView.tsx",
      "line": 143,
      "hex": "#2563EB",
      "snippet": "{statusDist.in_progress > 0 && <div style={{ width: `${statusDist.in_progress / total * 100}%`, background: '#2563EB' }} />}"
    },
    {
      "file": "src/pages/r360-member/ChronologyView.tsx",
      "line": 144,
      "hex": "#D97706",
      "snippet": "{statusDist.to_do > 0 && <div style={{ width: `${statusDist.to_do / total * 100}%`, background: '#D97706' }} />}"
    },
    {
      "file": "src/pages/r360-member/ChronologyView.tsx",
      "line": 145,
      "hex": "#EF4444",
      "snippet": "{statusDist.blocked > 0 && <div style={{ width: `${statusDist.blocked / total * 100}%`, background: '#EF4444' }} />}"
    },
    {
      "file": "src/pages/r360-member/ChronologyView.tsx",
      "line": 191,
      "hex": "#16A34A",
      "snippet": "{sd.done > 0 && <div style={{ width: `${sd.done / total * 100}%`, background: '#16A34A' }} />}"
    },
    {
      "file": "src/pages/r360-member/ChronologyView.tsx",
      "line": 192,
      "hex": "#2563EB",
      "snippet": "{sd.in_progress > 0 && <div style={{ width: `${sd.in_progress / total * 100}%`, background: '#2563EB' }} />}"
    },
    {
      "file": "src/pages/r360-member/ChronologyView.tsx",
      "line": 193,
      "hex": "#D97706",
      "snippet": "{sd.to_do > 0 && <div style={{ width: `${sd.to_do / total * 100}%`, background: '#D97706' }} />}"
    },
    {
      "file": "src/pages/r360-member/ChronologyView.tsx",
      "line": 194,
      "hex": "#EF4444",
      "snippet": "{sd.blocked > 0 && <div style={{ width: `${sd.blocked / total * 100}%`, background: '#EF4444' }} />}"
    },
    {
      "file": "src/pages/r360-member/ChronologyView.tsx",
      "line": 220,
      "hex": "#D97706",
      "snippet": "<span style={{ width: '10px', height: '10px', borderRadius: '50%', border: '2px solid #D97706', background: 'transparent', flexShrink: 0 }} "
    },
    {
      "file": "src/pages/r360-member/DetailPanel.tsx",
      "line": 42,
      "hex": "#7C3AED",
      "snippet": "<span style={{ display: 'inline-flex', alignItems: 'center', gap: '4px', fontSize: '10px', fontWeight: 600, padding: '2px 8px', borderRadius"
    },
    {
      "file": "src/pages/r360-member/DetailPanel.tsx",
      "line": 42,
      "hex": "#DDD6FE",
      "snippet": "<span style={{ display: 'inline-flex', alignItems: 'center', gap: '4px', fontSize: '10px', fontWeight: 600, padding: '2px 8px', borderRadius"
    },
    {
      "file": "src/pages/r360-member/DetailPanel.tsx",
      "line": 83,
      "hex": "#2563EB",
      "snippet": ": item.item_type === 'Sub-task' && item.parent_key ? <span style={{ color: '#2563EB', fontSize: 12 }}>Inherited from {item.parent_key}</span"
    },
    {
      "file": "src/pages/r360-member/DetailPanel.tsx",
      "line": 91,
      "hex": "#2563EB",
      "snippet": ": item.item_type === 'Sub-task' && item.parent_key ? <span style={{ color: '#2563EB', fontSize: 12 }}>Inherited from {item.parent_key}</span"
    },
    {
      "file": "src/pages/r360-member/RingView.tsx",
      "line": 112,
      "hex": "#1B7F37",
      "snippet": "width: '22px', height: '22px', borderRadius: '50%', background: '#1B7F37',"
    },
    {
      "file": "src/pages/r360-member/RingView.tsx",
      "line": 113,
      "hex": "#16A34A",
      "snippet": "border: '1.5px solid #16A34A', display: 'flex', alignItems: 'center', justifyContent: 'center', flexShrink: 0,"
    },
    {
      "file": "src/pages/r360-member/RingView.tsx",
      "line": 115,
      "hex": "#16A34A",
      "snippet": "<svg width=\"12\" height=\"12\" viewBox=\"0 0 12 12\"><path d=\"M2.5 6l2.5 2.5 4.5-4.5\" stroke=\"#16A34A\" strokeWidth=\"2\" fill=\"none\" strokeLinecap="
    },
    {
      "file": "src/pages/r360-member/RingView.tsx",
      "line": 118,
      "hex": "#1B7F37",
      "snippet": "<span style={{ fontSize: '11px', fontWeight: 700, color: '#FFFFFF', background: '#1B7F37', padding: '2px 8px', borderRadius: '12px' }}>{done"
    },
    {
      "file": "src/pages/r360-member/RingView.tsx",
      "line": 136,
      "hex": "#F8FAFC",
      "snippet": "style={{ display: 'flex', alignItems: 'flex-start', gap: '10px', padding: '10px 16px', cursor: 'pointer', borderBottom: '1px solid #F8FAFC',"
    },
    {
      "file": "src/pages/r360-member/RingView.tsx",
      "line": 143,
      "hex": "#2563EB",
      "snippet": "<span style={{ fontSize: '11.5px', fontWeight: 600, color: '#2563EB', fontFamily: 'var(--cp-font-mono)' }}>{item.item_key}</span>"
    },
    {
      "file": "src/pages/r360-member/RingView.tsx",
      "line": 179,
      "hex": "#2563EB",
      "snippet": "background: avatarUrl ? '#FFFFFF' : 'linear-gradient(135deg,#2563EB,#0D9488)',"
    }
  ],
  "NotifyHub": [
    {
      "file": "src/components/notifications/AgeingSkeleton.tsx",
      "line": 23,
      "hex": "#1A1A1A",
      "snippet": "? 'linear-gradient(90deg, #1A1A1A 25%, #292929 50%, #1A1A1A 75%)'"
    },
    {
      "file": "src/components/notifications/AgeingSkeleton.tsx",
      "line": 23,
      "hex": "#292929",
      "snippet": "? 'linear-gradient(90deg, #1A1A1A 25%, #292929 50%, #1A1A1A 75%)'"
    },
    {
      "file": "src/components/notifications/AgeingSkeleton.tsx",
      "line": 23,
      "hex": "#1A1A1A",
      "snippet": "? 'linear-gradient(90deg, #1A1A1A 25%, #292929 50%, #1A1A1A 75%)'"
    },
    {
      "file": "src/components/notifications/AgeingSkeleton.tsx",
      "line": 24,
      "hex": "#F1F5F9",
      "snippet": ": 'linear-gradient(90deg, #F1F5F9 25%, #E2E8F0 50%, #F1F5F9 75%)',"
    },
    {
      "file": "src/components/notifications/AgeingSkeleton.tsx",
      "line": 24,
      "hex": "#E2E8F0",
      "snippet": ": 'linear-gradient(90deg, #F1F5F9 25%, #E2E8F0 50%, #F1F5F9 75%)',"
    },
    {
      "file": "src/components/notifications/AgeingSkeleton.tsx",
      "line": 24,
      "hex": "#F1F5F9",
      "snippet": ": 'linear-gradient(90deg, #F1F5F9 25%, #E2E8F0 50%, #F1F5F9 75%)',"
    },
    {
      "file": "src/components/notifications/AgeingSkeleton.tsx",
      "line": 41,
      "hex": "#2E2E2E",
      "snippet": "borderBottom: isDark ? '0.75px solid #2E2E2E' : '0.75px solid #E2E8F0',"
    },
    {
      "file": "src/components/notifications/AgeingSkeleton.tsx",
      "line": 41,
      "hex": "#E2E8F0",
      "snippet": "borderBottom: isDark ? '0.75px solid #2E2E2E' : '0.75px solid #E2E8F0',"
    },
    {
      "file": "src/components/notifications/AgeingSkeleton.tsx",
      "line": 42,
      "hex": "#2E2E2E",
      "snippet": "borderTop: isDark ? '0.75px solid #2E2E2E' : '0.75px solid #E2E8F0',"
    },
    {
      "file": "src/components/notifications/AgeingSkeleton.tsx",
      "line": 42,
      "hex": "#E2E8F0",
      "snippet": "borderTop: isDark ? '0.75px solid #2E2E2E' : '0.75px solid #E2E8F0',"
    },
    {
      "file": "src/components/notifications/AgeingSkeleton.tsx",
      "line": 63,
      "hex": "#1F1F1F",
      "snippet": "<td style={{ padding: '8px 14px', borderBottom: isDark ? '0.75px solid #1F1F1F' : '0.75px solid #F1F5F9' }}>"
    },
    {
      "file": "src/components/notifications/AgeingSkeleton.tsx",
      "line": 63,
      "hex": "#F1F5F9",
      "snippet": "<td style={{ padding: '8px 14px', borderBottom: isDark ? '0.75px solid #1F1F1F' : '0.75px solid #F1F5F9' }}>"
    },
    {
      "file": "src/components/notifications/AgeingSkeleton.tsx",
      "line": 66,
      "hex": "#1F1F1F",
      "snippet": "<td style={{ padding: '8px 6px', borderBottom: isDark ? '0.75px solid #1F1F1F' : '0.75px solid #F1F5F9' }}>"
    },
    {
      "file": "src/components/notifications/AgeingSkeleton.tsx",
      "line": 66,
      "hex": "#F1F5F9",
      "snippet": "<td style={{ padding: '8px 6px', borderBottom: isDark ? '0.75px solid #1F1F1F' : '0.75px solid #F1F5F9' }}>"
    },
    {
      "file": "src/components/notifications/AgeingSkeleton.tsx",
      "line": 69,
      "hex": "#1F1F1F",
      "snippet": "<td style={{ padding: '8px 6px', borderBottom: isDark ? '0.75px solid #1F1F1F' : '0.75px solid #F1F5F9' }}>"
    },
    {
      "file": "src/components/notifications/AgeingSkeleton.tsx",
      "line": 69,
      "hex": "#F1F5F9",
      "snippet": "<td style={{ padding: '8px 6px', borderBottom: isDark ? '0.75px solid #1F1F1F' : '0.75px solid #F1F5F9' }}>"
    },
    {
      "file": "src/components/notifications/AgeingSkeleton.tsx",
      "line": 72,
      "hex": "#1F1F1F",
      "snippet": "<td style={{ padding: '8px 6px', borderBottom: isDark ? '0.75px solid #1F1F1F' : '0.75px solid #F1F5F9' }}>"
    },
    {
      "file": "src/components/notifications/AgeingSkeleton.tsx",
      "line": 72,
      "hex": "#F1F5F9",
      "snippet": "<td style={{ padding: '8px 6px', borderBottom: isDark ? '0.75px solid #1F1F1F' : '0.75px solid #F1F5F9' }}>"
    },
    {
      "file": "src/components/notifications/AgeingSkeleton.tsx",
      "line": 75,
      "hex": "#1F1F1F",
      "snippet": "<td style={{ padding: '8px 6px', borderBottom: isDark ? '0.75px solid #1F1F1F' : '0.75px solid #F1F5F9' }}>"
    },
    {
      "file": "src/components/notifications/AgeingSkeleton.tsx",
      "line": 75,
      "hex": "#F1F5F9",
      "snippet": "<td style={{ padding: '8px 6px', borderBottom: isDark ? '0.75px solid #1F1F1F' : '0.75px solid #F1F5F9' }}>"
    },
    {
      "file": "src/components/notifications/AgeingSkeleton.tsx",
      "line": 95,
      "hex": "#2E2E2E",
      "snippet": "borderBottom: isDark ? '0.75px solid #2E2E2E' : '0.75px solid #F1F5F9',"
    },
    {
      "file": "src/components/notifications/AgeingSkeleton.tsx",
      "line": 95,
      "hex": "#F1F5F9",
      "snippet": "borderBottom: isDark ? '0.75px solid #2E2E2E' : '0.75px solid #F1F5F9',"
    },
    {
      "file": "src/components/notifications/AgeingSkeleton.tsx",
      "line": 108,
      "hex": "#2E2E2E",
      "snippet": "borderBottom: isDark ? '0.75px solid #2E2E2E' : '0.75px solid #F1F5F9',"
    },
    {
      "file": "src/components/notifications/AgeingSkeleton.tsx",
      "line": 108,
      "hex": "#F1F5F9",
      "snippet": "borderBottom: isDark ? '0.75px solid #2E2E2E' : '0.75px solid #F1F5F9',"
    },
    {
      "file": "src/components/notifications/AgeingTab.tsx",
      "line": 140,
      "hex": "#63BA3C",
      "snippet": "<path fill=\"#63BA3C\" fillRule=\"evenodd\" d=\"M3,0 L21,0 C22.657,0 24,1.343 24,3 L24,21 C24,22.657 22.657,24 21,24 L3,24 C1.343,24 0,22.657 0,2"
    },
    {
      "file": "src/components/notifications/AgeingTab.tsx",
      "line": 146,
      "hex": "#63BA3C",
      "snippet": "<path fill=\"#63BA3C\" fillRule=\"evenodd\" d=\"M13,11 L13,5 C13,4.448 12.552,4 12,4 C11.448,4 11,4.448 11,5 L11,11 L5,11 C4.448,11 4,11.448 4,12"
    },
    {
      "file": "src/components/notifications/AgeingTab.tsx",
      "line": 152,
      "hex": "#4BADE8",
      "snippet": "<path fill=\"#4BADE8\" fillRule=\"evenodd\" d=\"M3,0 L21,0 C22.657,0 24,1.343 24,3 L24,21 C24,22.657 22.657,24 21,24 L3,24 C1.343,24 0,22.657 0,2"
    },
    {
      "file": "src/components/notifications/AgeingTab.tsx",
      "line": 158,
      "hex": "#E5493A",
      "snippet": "<path fill=\"#E5493A\" fillRule=\"evenodd\" d=\"M3,0 L21,0 C22.657,0 24,1.343 24,3 L24,21 C24,22.657 22.657,24 21,24 L3,24 C1.343,24 0,22.657 0,2"
    },
    {
      "file": "src/components/notifications/AgeingTab.tsx",
      "line": 164,
      "hex": "#E5493A",
      "snippet": "<path fill=\"#E5493A\" fillRule=\"evenodd\" d=\"M3,0 L21,0 C22.657,0 24,1.343 24,3 L24,21 C24,22.657 22.657,24 21,24 L3,24 C1.343,24 0,22.657 0,2"
    },
    {
      "file": "src/components/notifications/AgeingTab.tsx",
      "line": 304,
      "hex": "#EF4444",
      "snippet": "- Non-Atlaskit hexes (#EF4444, #F59E0B, #22C55E, #991B1B…) are replaced"
    }
  ],
  "Admin": [
    {
      "file": "src/pages/admin/AdminOverview.tsx",
      "line": 263,
      "hex": "#2563eb",
      "snippet": "<Button variant=\"ghost\" size=\"sm\" asChild className=\"text-xs text-[#2563eb] hover:text-[#1d4ed8]\">"
    },
    {
      "file": "src/pages/admin/AdminOverview.tsx",
      "line": 263,
      "hex": "#1d4ed8",
      "snippet": "<Button variant=\"ghost\" size=\"sm\" asChild className=\"text-xs text-[#2563eb] hover:text-[#1d4ed8]\">"
    },
    {
      "file": "src/pages/admin/CapacityDepartments.tsx",
      "line": 116,
      "hex": "#2563eb",
      "snippet": "className=\"gap-2 bg-[#2563eb] hover:bg-[#1d4ed8]\""
    },
    {
      "file": "src/pages/admin/CapacityDepartments.tsx",
      "line": 116,
      "hex": "#1d4ed8",
      "snippet": "className=\"gap-2 bg-[#2563eb] hover:bg-[#1d4ed8]\""
    },
    {
      "file": "src/pages/admin/CapacityDepartments.tsx",
      "line": 207,
      "hex": "#2563eb",
      "snippet": "className=\"bg-[#2563eb] hover:bg-[#1d4ed8]\""
    },
    {
      "file": "src/pages/admin/CapacityDepartments.tsx",
      "line": 207,
      "hex": "#1d4ed8",
      "snippet": "className=\"bg-[#2563eb] hover:bg-[#1d4ed8]\""
    },
    {
      "file": "src/pages/admin/CapacityDepartments.tsx",
      "line": 236,
      "hex": "#2563eb",
      "snippet": "className=\"bg-[#2563eb] hover:bg-[#1d4ed8]\""
    },
    {
      "file": "src/pages/admin/CapacityDepartments.tsx",
      "line": 236,
      "hex": "#1d4ed8",
      "snippet": "className=\"bg-[#2563eb] hover:bg-[#1d4ed8]\""
    },
    {
      "file": "src/pages/admin/FeatureFlagsPage.tsx",
      "line": 43,
      "hex": "#0C66E4",
      "snippet": "blue:    { bg: '#0C66E4', text: '#FFFFFF' },"
    },
    {
      "file": "src/pages/admin/FeatureFlagsPage.tsx",
      "line": 44,
      "hex": "#1B7F37",
      "snippet": "teal:    { bg: '#1B7F37', text: '#FFFFFF' },"
    },
    {
      "file": "src/pages/admin/FeatureFlagsPage.tsx",
      "line": 45,
      "hex": "#FFEBE6",
      "snippet": "red:     { bg: '#FFEBE6', text: '#BF2600' },"
    },
    {
      "file": "src/pages/admin/FeatureFlagsPage.tsx",
      "line": 45,
      "hex": "#BF2600",
      "snippet": "red:     { bg: '#FFEBE6', text: '#BF2600' },"
    },
    {
      "file": "src/pages/admin/FeatureFlagsPage.tsx",
      "line": 46,
      "hex": "#DFE1E6",
      "snippet": "neutral: { bg: '#DFE1E6', text: '#42526E' },"
    },
    {
      "file": "src/pages/admin/FeatureFlagsPage.tsx",
      "line": 46,
      "hex": "#42526E",
      "snippet": "neutral: { bg: '#DFE1E6', text: '#42526E' },"
    },
    {
      "file": "src/pages/admin/FeatureFlagsPage.tsx",
      "line": 51,
      "hex": "#1B7F37",
      "snippet": "live:  { bg: '#1B7F37', text: '#FFFFFF' },"
    },
    {
      "file": "src/pages/admin/FeatureFlagsPage.tsx",
      "line": 52,
      "hex": "#DFE1E6",
      "snippet": "draft: { bg: '#DFE1E6', text: '#42526E' },"
    },
    {
      "file": "src/pages/admin/FeatureFlagsPage.tsx",
      "line": 52,
      "hex": "#42526E",
      "snippet": "draft: { bg: '#DFE1E6', text: '#42526E' },"
    },
    {
      "file": "src/pages/admin/FeatureFlagsPage.tsx",
      "line": 53,
      "hex": "#0C66E4",
      "snippet": "beta:  { bg: '#0C66E4', text: '#FFFFFF' },"
    },
    {
      "file": "src/pages/admin/FeatureFlagsPage.tsx",
      "line": 58,
      "hex": "#EFF6FF",
      "snippet": "Strategy:   { bg: '#EFF6FF', text: '#2563EB', border: '#BFDBFE' },"
    },
    {
      "file": "src/pages/admin/FeatureFlagsPage.tsx",
      "line": 58,
      "hex": "#2563EB",
      "snippet": "Strategy:   { bg: '#EFF6FF', text: '#2563EB', border: '#BFDBFE' },"
    },
    {
      "file": "src/pages/admin/FeatureFlagsPage.tsx",
      "line": 58,
      "hex": "#BFDBFE",
      "snippet": "Strategy:   { bg: '#EFF6FF', text: '#2563EB', border: '#BFDBFE' },"
    },
    {
      "file": "src/pages/admin/FeatureFlagsPage.tsx",
      "line": 59,
      "hex": "#F4F4F5",
      "snippet": "Product:    { bg: '#F4F4F5', text: '#3F3F46', border: '#D4D4D8' },"
    },
    {
      "file": "src/pages/admin/FeatureFlagsPage.tsx",
      "line": 59,
      "hex": "#3F3F46",
      "snippet": "Product:    { bg: '#F4F4F5', text: '#3F3F46', border: '#D4D4D8' },"
    },
    {
      "file": "src/pages/admin/FeatureFlagsPage.tsx",
      "line": 59,
      "hex": "#D4D4D8",
      "snippet": "Product:    { bg: '#F4F4F5', text: '#3F3F46', border: '#D4D4D8' },"
    },
    {
      "file": "src/pages/admin/FeatureFlagsPage.tsx",
      "line": 60,
      "hex": "#EFF6FF",
      "snippet": "Delivery:   { bg: '#EFF6FF', text: '#2563EB', border: '#BFDBFE' },"
    },
    {
      "file": "src/pages/admin/FeatureFlagsPage.tsx",
      "line": 60,
      "hex": "#2563EB",
      "snippet": "Delivery:   { bg: '#EFF6FF', text: '#2563EB', border: '#BFDBFE' },"
    },
    {
      "file": "src/pages/admin/FeatureFlagsPage.tsx",
      "line": 60,
      "hex": "#BFDBFE",
      "snippet": "Delivery:   { bg: '#EFF6FF', text: '#2563EB', border: '#BFDBFE' },"
    },
    {
      "file": "src/pages/admin/FeatureFlagsPage.tsx",
      "line": 61,
      "hex": "#F0FDFA",
      "snippet": "Quality:    { bg: '#F0FDFA', text: '#0D9488', border: '#99F6E4' },"
    },
    {
      "file": "src/pages/admin/FeatureFlagsPage.tsx",
      "line": 61,
      "hex": "#0D9488",
      "snippet": "Quality:    { bg: '#F0FDFA', text: '#0D9488', border: '#99F6E4' },"
    },
    {
      "file": "src/pages/admin/FeatureFlagsPage.tsx",
      "line": 61,
      "hex": "#99F6E4",
      "snippet": "Quality:    { bg: '#F0FDFA', text: '#0D9488', border: '#99F6E4' },"
    }
  ],
  "ReqAssist": [
    {
      "file": "src/components/reqAssist/RABackgroundModal.tsx",
      "line": 150,
      "hex": "#FEF2F2",
      "snippet": "<div style={{ width: 48, height: 48, borderRadius: 12, background: jobStatus === 'failed' ? '#FEF2F2' : jobStatus === 'done' ? '#F0FDF4' : '"
    },
    {
      "file": "src/components/reqAssist/RABackgroundModal.tsx",
      "line": 150,
      "hex": "#F0FDF4",
      "snippet": "<div style={{ width: 48, height: 48, borderRadius: 12, background: jobStatus === 'failed' ? '#FEF2F2' : jobStatus === 'done' ? '#F0FDF4' : '"
    },
    {
      "file": "src/components/reqAssist/RABackgroundModal.tsx",
      "line": 200,
      "hex": "#DCFCE7",
      "snippet": "<div style={{ width: 22, height: 22, borderRadius: '50%', display: 'flex', alignItems: 'center', justifyContent: 'center', background: isDon"
    },
    {
      "file": "src/components/reqAssist/RABackgroundModal.tsx",
      "line": 200,
      "hex": "#DBEAFE",
      "snippet": "<div style={{ width: 22, height: 22, borderRadius: '50%', display: 'flex', alignItems: 'center', justifyContent: 'center', background: isDon"
    },
    {
      "file": "src/components/reqAssist/RABackgroundModal.tsx",
      "line": 213,
      "hex": "#DBEAFE",
      "snippet": "<div style={{ display: 'flex', alignItems: 'center', gap: 8, padding: '14px 14px', background: 'var(--cp-primary-5)', borderRadius: 'var(--r"
    },
    {
      "file": "src/components/reqAssist/RABackgroundModal.tsx",
      "line": 215,
      "hex": "#1E40AF",
      "snippet": "<span style={{ fontSize: 12, color: '#1E40AF', fontFamily: 'var(--cp-font-body)' }}>Estimated: {etaLabel} · You'll be notified when done</sp"
    },
    {
      "file": "src/components/reqAssist/RABackgroundModal.tsx",
      "line": 230,
      "hex": "#CBD5E1",
      "snippet": "<button onClick={handleLeave} style={{ padding: '8px 16px', fontSize: 13, fontWeight: 500, border: '0.75px solid #CBD5E1', borderRadius: 'va"
    },
    {
      "file": "src/components/reqAssist/RAEpicDraftDrawer.tsx",
      "line": 31,
      "hex": "#DFE1E6",
      "snippet": "draft:     { bg: '#DFE1E6', color: '#42526E', label: 'DRAFT' },"
    },
    {
      "file": "src/components/reqAssist/RAEpicDraftDrawer.tsx",
      "line": 31,
      "hex": "#42526E",
      "snippet": "draft:     { bg: '#DFE1E6', color: '#42526E', label: 'DRAFT' },"
    },
    {
      "file": "src/components/reqAssist/RAEpicDraftDrawer.tsx",
      "line": 32,
      "hex": "#0C66E4",
      "snippet": "reviewed:  { bg: '#0C66E4', color: '#FFFFFF', label: 'REVIEWED' },"
    },
    {
      "file": "src/components/reqAssist/RAEpicDraftDrawer.tsx",
      "line": 33,
      "hex": "#1B7F37",
      "snippet": "published: { bg: '#1B7F37', color: '#FFFFFF', label: 'PUBLISHED' },"
    },
    {
      "file": "src/components/reqAssist/RAEpicDraftDrawer.tsx",
      "line": 187,
      "hex": "#0C66E4",
      "snippet": "margin: '12px 20px 0', background: '#0C66E4', border: '1px solid #B3D4FF',"
    },
    {
      "file": "src/components/reqAssist/RAEpicDraftDrawer.tsx",
      "line": 187,
      "hex": "#B3D4FF",
      "snippet": "margin: '12px 20px 0', background: '#0C66E4', border: '1px solid #B3D4FF',"
    },
    {
      "file": "src/components/reqAssist/RAEpicDraftDrawer.tsx",
      "line": 236,
      "hex": "#2E2E2E",
      "snippet": "border: isDark ? '0.75px solid #2E2E2E' : '0.75px solid #CBD5E1',"
    },
    {
      "file": "src/components/reqAssist/RAEpicDraftDrawer.tsx",
      "line": 236,
      "hex": "#CBD5E1",
      "snippet": "border: isDark ? '0.75px solid #2E2E2E' : '0.75px solid #CBD5E1',"
    },
    {
      "file": "src/components/reqAssist/RAEpicDraftDrawer.tsx",
      "line": 254,
      "hex": "#CBD5E1",
      "snippet": "border: '1px solid #CBD5E1', borderRadius: 4, padding: '6px 8px',"
    },
    {
      "file": "src/components/reqAssist/RAEpicDraftDrawer.tsx",
      "line": 258,
      "hex": "#CBD5E1",
      "snippet": "onBlur={e => (e.currentTarget.style.borderColor = '#CBD5E1')}"
    },
    {
      "file": "src/components/reqAssist/RAEpicDraftDrawer.tsx",
      "line": 266,
      "hex": "#CBD5E1",
      "snippet": "border: '1px solid #CBD5E1', borderRadius: 4, padding: '6px 8px',"
    },
    {
      "file": "src/components/reqAssist/RAEpicDraftDrawer.tsx",
      "line": 271,
      "hex": "#CBD5E1",
      "snippet": "onBlur={e => (e.currentTarget.style.borderColor = '#CBD5E1')}"
    },
    {
      "file": "src/components/reqAssist/RAEpicDraftDrawer.tsx",
      "line": 312,
      "hex": "#2E2E2E",
      "snippet": "borderRadius: 6, border: isDark ? '0.75px solid #2E2E2E' : '0.75px solid rgba(15,23,42,0.15)',"
    },
    {
      "file": "src/components/reqAssist/RAEpicDraftDrawer.tsx",
      "line": 408,
      "hex": "#1D4ED8",
      "snippet": "onMouseEnter={e => (e.currentTarget.style.background = '#1D4ED8')}"
    },
    {
      "file": "src/components/reqAssist/RAEpicGenerationModal.tsx",
      "line": 240,
      "hex": "#F0FDF4",
      "snippet": "width: 64, height: 64, borderRadius: '50%', background: '#F0FDF4',"
    },
    {
      "file": "src/components/reqAssist/RAEpicGenerationModal.tsx",
      "line": 258,
      "hex": "#DCFCE7",
      "snippet": "width: 28, height: 28, borderRadius: '50%', background: '#DCFCE7',"
    },
    {
      "file": "src/components/reqAssist/RAEpicGenerationModal.tsx",
      "line": 269,
      "hex": "#F3F4F6",
      "snippet": "<div style={{ width: '100%', height: 6, borderRadius: 999, background: '#F3F4F6', marginBottom: 20, overflow: 'hidden' }}>"
    },
    {
      "file": "src/components/reqAssist/RAEpicGenerationModal.tsx",
      "line": 279,
      "hex": "#CBD5E1",
      "snippet": "border: '0.75px solid #CBD5E1', background: 'var(--bg-app)', color: 'var(--fg-2)', cursor: 'pointer',"
    },
    {
      "file": "src/components/reqAssist/RAEpicGenerationModal.tsx",
      "line": 309,
      "hex": "#FEF2F2",
      "snippet": "width: 56, height: 56, borderRadius: '50%', background: '#FEF2F2',"
    },
    {
      "file": "src/components/reqAssist/RAEpicGenerationModal.tsx",
      "line": 320,
      "hex": "#FEF2F2",
      "snippet": "background: '#FEF2F2', border: '1.5px solid #DC2626', borderRadius: 6,"
    },
    {
      "file": "src/components/reqAssist/RAEpicGenerationModal.tsx",
      "line": 320,
      "hex": "#DC2626",
      "snippet": "background: '#FEF2F2', border: '1.5px solid #DC2626', borderRadius: 6,"
    },
    {
      "file": "src/components/reqAssist/RAEpicGenerationModal.tsx",
      "line": 324,
      "hex": "#991B1B",
      "snippet": "fontSize: 13, color: '#991B1B', lineHeight: 1.5, whiteSpace: 'pre-wrap', wordBreak: 'break-all' as const,"
    },
    {
      "file": "src/components/reqAssist/RAEpicGenerationModal.tsx",
      "line": 336,
      "hex": "#F3F4F6",
      "snippet": "<div style={{ width: '100%', height: 6, borderRadius: 999, background: '#F3F4F6', marginBottom: 20, overflow: 'hidden' }}>"
    }
  ]
}